[
  {
    "id": "bugatti_chiron",
    "name": "Bugatti Chiron",
    "rank": 1,
    "car_class": "S",
    "top_speed": 491,
    "acceleration": 46,
    "handling": 36,
    "nitro": 47,
    "n_top_speed": 0.8823000898472596,
    "n_acceleration": 0.5081749889527176,
    "n_handling": 0.3535998428445143,
    "n_nitro": 0.5440444495890728
  },
  {
    "id": "ferrari_f40",
    "name": "Ferrari F40",
    "rank": 2,
    "car_class": "S",
    "top_speed": 440,
    "acceleration": 52,
    "handling": 44,
    "nitro": 48,
    "n_top_speed": 0.7906558849955077,
    "n_acceleration": 0.5744586831639417,
    "n_handling": 0.4321775856988508,
    "n_nitro": 0.5556198634101169
  },
  {
    "id": "mclaren_p1",
    "name": "McLaren P1",
    "rank": 3,
    "car_class": "S",
    "top_speed": 380,
    "acceleration": 58,
    "handling": 58,
    "nitro": 55,
    "n_top_speed": 0.6828391734052112,
    "n_acceleration": 0.6407423773751657,
    "n_handling": 0.5696886356939397,
    "n_nitro": 0.6366477601574256
  },
  {
    "id": "lamborghini_huracan",
    "name": "Lamborghini Huracan",
    "rank": 4,
    "car_class": "A",
    "top_speed": 360,
    "acceleration": 55,
    "handling": 50,
    "nitro": 60,
    "n_top_speed": 0.6469002695417789,
    "n_acceleration": 0.6076005302695537,
    "n_handling": 0.4911108928396032,
    "n_nitro": 0.6945248292626461
  },
  {
    "id": "porsche_911_gt3",
    "name": "Porsche 911 GT3",
    "rank": 5,
    "car_class": "A",
    "top_speed": 320,
    "acceleration": 48,
    "handling": 65,
    "nitro": 45,
    "n_top_speed": 0.5750224618149147,
    "n_acceleration": 0.5302695536897923,
    "n_handling": 0.6384441606914841,
    "n_nitro": 0.5208936219469846
  },
  {
    "id": "mitsubishi_lancer_evolution",
    "name": "Mitsubishi Lancer Evolution",
    "rank": 0,
    "car_class": "D",
    "top_speed": 270.1,
    "acceleration": 55.03,
    "handling": 53.79,
    "nitro": 68.19,
    "n_top_speed": 0.48535489667565146,
    "n_acceleration": 0.6079319487406099,
    "n_handling": 0.5283370985168451,
    "n_nitro": 0.7893274684569973
  },
  {
    "id": "bmw_z4_lci_e89",
    "name": "BMW Z4 LCI E89",
    "rank": 0,
    "car_class": "D",
    "top_speed": 266.8,
    "acceleration": 68.86,
    "handling": 47.43,
    "nitro": 57.49,
    "n_top_speed": 0.4794249775381851,
    "n_acceleration": 0.7607158638974812,
    "n_handling": 0.4658677929476476,
    "n_nitro": 0.6654705405718254
  },
  {
    "id": "chevrolet_camaro_lt",
    "name": "Chevrolet Camaro Lt",
    "rank": 0,
    "car_class": "D",
    "top_speed": 284.1,
    "acceleration": 64.81,
    "handling": 48.39,
    "nitro": 63.29,
    "n_top_speed": 0.510512129380054,
    "n_acceleration": 0.7159743703049051,
    "n_handling": 0.47529712209016794,
    "n_nitro": 0.7326079407338812
  },
  {
    "id": "nissan_leaf_nismo_rc",
    "name": "Nissan Leaf Nismo Rc",
    "rank": 0,
    "car_class": "D",
    "top_speed": 244.5,
    "acceleration": 78.87,
    "handling": 59.91,
    "nitro": 65.03,
    "n_top_speed": 0.4393530997304582,
    "n_acceleration": 0.8712991604065401,
    "n_handling": 0.5884490718004125,
    "n_nitro": 0.752749160782498
  },
  {
    "id": "nissan_370z_nismo",
    "name": "Nissan 370Z Nismo",
    "rank": 0,
    "car_class": "D",
    "top_speed": 268.5,
    "acceleration": 66.61,
    "handling": 81.83,
    "nitro": 67.07,
    "n_top_speed": 0.48247978436657685,
    "n_acceleration": 0.7358594785682723,
    "n_handling": 0.8037520872212945,
    "n_nitro": 0.7763630049774278
  },
  {
    "id": "ktm_x_bow_gtx",
    "name": "Ktm X-Bow GTX",
    "rank": 0,
    "car_class": "D",
    "top_speed": 247.5,
    "acceleration": 83.84,
    "handling": 64.99,
    "nitro": 66.99,
    "n_top_speed": 0.444743935309973,
    "n_acceleration": 0.9262041537781707,
    "n_handling": 0.6383459385129161,
    "n_nitro": 0.7754369718717443
  },
  {
    "id": "volkswagen_xl_sport_concept",
    "name": "Volkswagen XL Sport Concept",
    "rank": 0,
    "car_class": "D",
    "top_speed": 291.2,
    "acceleration": 60.31,
    "handling": 62.02,
    "nitro": 61.94,
    "n_top_speed": 0.5232704402515723,
    "n_acceleration": 0.666261599646487,
    "n_handling": 0.6091739514782438,
    "n_nitro": 0.7169811320754716
  },
  {
    "id": "ds_automobiles_ds_e_tense",
    "name": "DS Automobiles DS E-Tense",
    "rank": 0,
    "car_class": "D",
    "top_speed": 270.1,
    "acceleration": 76.07,
    "handling": 81.27,
    "nitro": 72.3,
    "n_top_speed": 0.48535489667565146,
    "n_acceleration": 0.8403667697746354,
    "n_handling": 0.798251645221491,
    "n_nitro": 0.8369024192614886
  },
  {
    "id": "dodge_challanger_392_hemi_scat_pack",
    "name": "Dodge Challanger 392 Hemi Scat Pack",
    "rank": 0,
    "car_class": "D",
    "top_speed": 299.3,
    "acceleration": 72.46,
    "handling": 43.24,
    "nitro": 62.34,
    "n_top_speed": 0.5378256963162624,
    "n_acceleration": 0.8004860804242157,
    "n_handling": 0.42471270012768886,
    "n_nitro": 0.7216112976038894
  },
  {
    "id": "renault_dezir",
    "name": "Renault Dezir",
    "rank": 0,
    "car_class": "D",
    "top_speed": 293.2,
    "acceleration": 65.56,
    "handling": 69.43,
    "nitro": 68.44,
    "n_top_speed": 0.5268643306379155,
    "n_acceleration": 0.7242598320813081,
    "n_handling": 0.6819565857970731,
    "n_nitro": 0.7922213219122584
  },
  {
    "id": "italdesign_davinci",
    "name": "Italdesign Davinci",
    "rank": 0,
    "car_class": "D",
    "top_speed": 278.3,
    "acceleration": 83.53,
    "handling": 73.57,
    "nitro": 55.35,
    "n_top_speed": 0.5000898472596585,
    "n_acceleration": 0.9227794962439241,
    "n_handling": 0.722620567724192,
    "n_nitro": 0.6406991549947911
  },
  {
    "id": "bmw_i8_roadster",
    "name": "BMW i8 Roadster",
    "rank": 0,
    "car_class": "D",
    "top_speed": 278.3,
    "acceleration": 79.72,
    "handling": 78.61,
    "nitro": 66.88,
    "n_top_speed": 0.5000898472596585,
    "n_acceleration": 0.8806893504197968,
    "n_handling": 0.7721245457224241,
    "n_nitro": 0.7741636763514295
  },
  {
    "id": "peugeot_sr1",
    "name": "Peugeot SR1",
    "rank": 0,
    "car_class": "D",
    "top_speed": 305.8,
    "acceleration": 67.7,
    "handling": 46.85,
    "nitro": 25.95,
    "n_top_speed": 0.5495058400718779,
    "n_acceleration": 0.747901016349978,
    "n_handling": 0.4601709065907082,
    "n_nitro": 0.30038198865609445
  },
  {
    "id": "porsche_911_carrera_rs_3_8",
    "name": "Porsche 911 Carrera RS 3.8",
    "rank": 0,
    "car_class": "D",
    "top_speed": 296.9,
    "acceleration": 70.52,
    "handling": 65.24,
    "nitro": 35.55,
    "n_top_speed": 0.5335130278526504,
    "n_acceleration": 0.7790543526292532,
    "n_handling": 0.6408014929771142,
    "n_nitro": 0.4115059613381178
  },
  {
    "id": "porsche_718_cayman",
    "name": "Porsche 718 Cayman",
    "rank": 0,
    "car_class": "D",
    "top_speed": 295.7,
    "acceleration": 70.52,
    "handling": 61.91,
    "nitro": 60.26,
    "n_top_speed": 0.5313566936208446,
    "n_acceleration": 0.7790543526292532,
    "n_handling": 0.6080935075139966,
    "n_nitro": 0.6975344368561176
  },
  {
    "id": "infiniti_project_black_s",
    "name": "Infiniti Project Black S",
    "rank": 0,
    "car_class": "D",
    "top_speed": 281.2,
    "acceleration": 76.19,
    "handling": 66.97,
    "nitro": 64.68,
    "n_top_speed": 0.5053009883198563,
    "n_acceleration": 0.84169244365886,
    "n_handling": 0.6577939298693645,
    "n_nitro": 0.7486977659451326
  },
  {
    "id": "lotus_elise_sprint_220",
    "name": "Lotus Elise Sprint 220",
    "rank": 0,
    "car_class": "D",
    "top_speed": 270.0,
    "acceleration": 82.25,
    "handling": 83.47,
    "nitro": 72.71,
    "n_top_speed": 0.48517520215633425,
    "n_acceleration": 0.9086389748121962,
    "n_handling": 0.8198605245064335,
    "n_nitro": 0.8416483389281166
  },
  {
    "id": "lamborghini_countach_25th_anniversary",
    "name": "Lamborghini Countach 25th Anniversary",
    "rank": 0,
    "car_class": "D",
    "top_speed": 304.9,
    "acceleration": 71.69,
    "handling": 55.89,
    "nitro": 36.3,
    "n_top_speed": 0.5478885893980233,
    "n_acceleration": 0.7919796730004419,
    "n_handling": 0.5489637560161085,
    "n_nitro": 0.4201875217039009
  },
  {
    "id": "ford_shelby_gt350r",
    "name": "Ford Shelby Gt350R",
    "rank": 0,
    "car_class": "D",
    "top_speed": 299.9,
    "acceleration": 75.06,
    "handling": 58.97,
    "nitro": 52.93,
    "n_top_speed": 0.5389038634321652,
    "n_acceleration": 0.8292090145824128,
    "n_handling": 0.579216187015028,
    "n_nitro": 0.6126866535478643
  },
  {
    "id": "porsche_911_targa_4s",
    "name": "Porsche 911 Targa 4S",
    "rank": 0,
    "car_class": "D",
    "top_speed": 315.1,
    "acceleration": 75.37,
    "handling": 41.57,
    "nitro": 38.35,
    "n_top_speed": 0.5662174303683738,
    "n_acceleration": 0.8326336721166594,
    "n_handling": 0.4083095963068461,
    "n_nitro": 0.4439171200370413
  },
  {
    "id": "lotus_emira",
    "name": "Lotus Emira",
    "rank": 0,
    "car_class": "D",
    "top_speed": 307.2,
    "acceleration": 70.87,
    "handling": 57.45,
    "nitro": 53.42,
    "n_top_speed": 0.552021563342318,
    "n_acceleration": 0.7829209014582413,
    "n_handling": 0.5642864158727041,
    "n_nitro": 0.6183586063201759
  },
  {
    "id": "praga_r1",
    "name": "Praga R1",
    "rank": 0,
    "car_class": "D",
    "top_speed": 283.3,
    "acceleration": 87.8,
    "handling": 62.25,
    "nitro": 60.92,
    "n_top_speed": 0.5090745732255166,
    "n_acceleration": 0.9699513919575784,
    "n_handling": 0.611433061585306,
    "n_nitro": 0.7051742099780067
  },
  {
    "id": "ginetta_g60",
    "name": "Ginetta G60",
    "rank": 0,
    "car_class": "D",
    "top_speed": 290.7,
    "acceleration": 71.51,
    "handling": 74.81,
    "nitro": 62.66,
    "n_top_speed": 0.5223719676549865,
    "n_acceleration": 0.7899911621741053,
    "n_handling": 0.7348001178666143,
    "n_nitro": 0.7253154300266234
  },
  {
    "id": "renault_trezor",
    "name": "Renault TreZor",
    "rank": 0,
    "car_class": "D",
    "top_speed": 294.5,
    "acceleration": 78.62,
    "handling": 61.93,
    "nitro": 61.07,
    "n_top_speed": 0.5292003593890386,
    "n_acceleration": 0.8685373398144057,
    "n_handling": 0.6082899518711324,
    "n_nitro": 0.7069105220511633
  },
  {
    "id": "nissan_370z_neon_edition",
    "name": "Nissan 370Z Neon Edition",
    "rank": 0,
    "car_class": "D",
    "top_speed": 271.1,
    "acceleration": 83.26,
    "handling": 82.91,
    "nitro": 65.22,
    "n_top_speed": 0.48715184186882304,
    "n_acceleration": 0.919796730004419,
    "n_handling": 0.81436008250663,
    "n_nitro": 0.7549484894084963
  },
  {
    "id": "honda_civic_type_r",
    "name": "Honda Civic Type-R",
    "rank": 0,
    "car_class": "D",
    "top_speed": 285.3,
    "acceleration": 82.09,
    "handling": 68.41,
    "nitro": 62.55,
    "n_top_speed": 0.5126684636118598,
    "n_acceleration": 0.9068714096332303,
    "n_handling": 0.6719379235831451,
    "n_nitro": 0.7240421345063086
  },
  {
    "id": "porsche_taycan_turbo_s",
    "name": "Porsche Taycan Turbo S",
    "rank": 0,
    "car_class": "D",
    "top_speed": 279.2,
    "acceleration": 83.74,
    "handling": 75.77,
    "nitro": 57.18,
    "n_top_speed": 0.501707097933513,
    "n_acceleration": 0.9250994255413169,
    "n_handling": 0.7442294470091346,
    "n_nitro": 0.6618821622873018
  },
  {
    "id": "tvr_griffith",
    "name": "TVR Griffith",
    "rank": 0,
    "car_class": "D",
    "top_speed": 338.7,
    "acceleration": 69.28,
    "handling": 47.31,
    "nitro": 37.49,
    "n_top_speed": 0.6086253369272236,
    "n_acceleration": 0.7653557224922669,
    "n_handling": 0.46468912680483254,
    "n_nitro": 0.4339622641509434
  },
  {
    "id": "bentley_continental_gt3",
    "name": "Bentley Continental GT3",
    "rank": 0,
    "car_class": "D",
    "top_speed": 300.8,
    "acceleration": 74.74,
    "handling": 72.52,
    "nitro": 50.79,
    "n_top_speed": 0.5405211141060198,
    "n_acceleration": 0.8256738842244807,
    "n_handling": 0.7123072389745604,
    "n_nitro": 0.5879152679708299
  },
  {
    "id": "mazda_furai",
    "name": "Mazda Furai",
    "rank": 0,
    "car_class": "D",
    "top_speed": 305.5,
    "acceleration": 80.95,
    "handling": 57.23,
    "nitro": 49.67,
    "n_top_speed": 0.5489667565139263,
    "n_acceleration": 0.8942775077330978,
    "n_handling": 0.5621255279442098,
    "n_nitro": 0.5749508044912606
  },
  {
    "id": "alfa_romeo_giulia_gtam",
    "name": "Alfa Romeo Giulia GTAm",
    "rank": 0,
    "car_class": "D",
    "top_speed": 312.2,
    "acceleration": 77.28,
    "handling": 45.17,
    "nitro": 47.09,
    "n_top_speed": 0.5610062893081761,
    "n_acceleration": 0.8537339814405657,
    "n_handling": 0.4436695805912975,
    "n_nitro": 0.5450862368329669
  },
  {
    "id": "chevrolet_corvette_c7_r",
    "name": "Chevrolet Corvette C7.R",
    "rank": 0,
    "car_class": "D",
    "top_speed": 307.6,
    "acceleration": 80.48,
    "handling": 47.08,
    "nitro": 57.03,
    "n_top_speed": 0.5527403414195867,
    "n_acceleration": 0.8890852850198852,
    "n_handling": 0.46243001669777034,
    "n_nitro": 0.6601458502141452
  },
  {
    "id": "aston_martin_vantage_v12_2022",
    "name": "Aston Martin Vantage V12 2022",
    "rank": 0,
    "car_class": "D",
    "top_speed": 331.1,
    "acceleration": 75.84,
    "handling": 39.15,
    "nitro": 42.5,
    "n_top_speed": 0.5949685534591196,
    "n_acceleration": 0.8378258948298719,
    "n_handling": 0.3845398290934093,
    "n_nitro": 0.4919550873943743
  },
  {
    "id": "lamborghini_huracan_super_trofeo_evo",
    "name": "Lamborghini Huracan Super Trofeo Evo",
    "rank": 0,
    "car_class": "D",
    "top_speed": 303.7,
    "acceleration": 82.59,
    "handling": 63.48,
    "nitro": 54.41,
    "n_top_speed": 0.5457322551662174,
    "n_acceleration": 0.9123950508174989,
    "n_handling": 0.6235143895491602,
    "n_nitro": 0.6298182660030096
  },
  {
    "id": "volkswagen_electric_r",
    "name": "Volkswagen Electric R",
    "rank": 0,
    "car_class": "D",
    "top_speed": 290.5,
    "acceleration": 88.5,
    "handling": 57.91,
    "nitro": 67.93,
    "n_top_speed": 0.5220125786163522,
    "n_acceleration": 0.9776844896155547,
    "n_handling": 0.5688046360868284,
    "n_nitro": 0.786317860863526
  },
  {
    "id": "glickenhaus_004c",
    "name": "Glickenhaus 004C",
    "rank": 0,
    "car_class": "D",
    "top_speed": 298.0,
    "acceleration": 70.3,
    "handling": 40.47,
    "nitro": 36.15,
    "n_top_speed": 0.5354896675651393,
    "n_acceleration": 0.776623950508175,
    "n_handling": 0.3975051566643748,
    "n_nitro": 0.4184512096307443
  },
  {
    "id": "ford_mustang_mach_e1400",
    "name": "Ford Mustang Mach-E1400",
    "rank": 0,
    "car_class": "D",
    "top_speed": 301.2,
    "acceleration": 82.87,
    "handling": 51.83,
    "nitro": 64.82,
    "n_top_speed": 0.5412398921832884,
    "n_acceleration": 0.9154882898806894,
    "n_handling": 0.5090855515175327,
    "n_nitro": 0.7503183238800786
  },
  {
    "id": "dodge_challenger_srt8",
    "name": "Dodge Challenger SRT8",
    "rank": 0,
    "car_class": "C",
    "top_speed": 308.6,
    "acceleration": 71.92,
    "handling": 39.84,
    "nitro": 46.24,
    "n_top_speed": 0.5545372866127584,
    "n_acceleration": 0.7945205479452055,
    "n_handling": 0.3913171594145958,
    "n_nitro": 0.5352471350850793
  },
  {
    "id": "bmw_3_0_csl_hommage",
    "name": "BMW 3.0 CSL Hommage",
    "rank": 0,
    "car_class": "C",
    "top_speed": 297.4,
    "acceleration": 73.39,
    "handling": 50.08,
    "nitro": 51.2,
    "n_top_speed": 0.5344115004492362,
    "n_acceleration": 0.8107600530269554,
    "n_handling": 0.49189667026814654,
    "n_nitro": 0.5926611876374581
  },
  {
    "id": "porsche_boxster_25th",
    "name": "Porsche Boxster 25th",
    "rank": 0,
    "car_class": "C",
    "top_speed": 298.4,
    "acceleration": 71.92,
    "handling": 45.93,
    "nitro": 53.86,
    "n_top_speed": 0.5362084456424079,
    "n_acceleration": 0.7945205479452055,
    "n_handling": 0.45113446616245945,
    "n_nitro": 0.6234517884014353
  },
  {
    "id": "chevrolet_camaro_zl1_50th_edition",
    "name": "Chevrolet Camaro ZL1 50th Edition",
    "rank": 0,
    "car_class": "C",
    "top_speed": 271.0,
    "acceleration": 78.14,
    "handling": 83.14,
    "nitro": 72.33,
    "n_top_speed": 0.48697214734950584,
    "n_acceleration": 0.8632346442775077,
    "n_handling": 0.8166191926136922,
    "n_nitro": 0.8372496816761199
  },
  {
    "id": "lotus_evora_sport_410",
    "name": "Lotus Evora Sport 410",
    "rank": 0,
    "car_class": "C",
    "top_speed": 317.7,
    "acceleration": 71.7,
    "handling": 50.93,
    "nitro": 47.05,
    "n_top_speed": 0.5708894878706199,
    "n_acceleration": 0.7920901458241273,
    "n_handling": 0.5002455554464198,
    "n_nitro": 0.544623220280125
  },
  {
    "id": "mercedes_benz_amg_gt_s",
    "name": "Mercedes-Benz AMG GT S",
    "rank": 0,
    "car_class": "C",
    "top_speed": 329.4,
    "acceleration": 71.34,
    "handling": 42.69,
    "nitro": 54.65,
    "n_top_speed": 0.5919137466307277,
    "n_acceleration": 0.7881131241714538,
    "n_handling": 0.4193104803064532,
    "n_nitro": 0.6325963653200601
  },
  {
    "id": "bmw_m4_gts",
    "name": "BMW M4 GTS",
    "rank": 0,
    "car_class": "C",
    "top_speed": 326.5,
    "acceleration": 73.72,
    "handling": 51.19,
    "nitro": 52.48,
    "n_top_speed": 0.5867026055705301,
    "n_acceleration": 0.8144056562085727,
    "n_handling": 0.5027993320891857,
    "n_nitro": 0.6074777173283944
  },
  {
    "id": "rezvani_beast_x",
    "name": "Rezvani Beast X",
    "rank": 0,
    "car_class": "C",
    "top_speed": 299.5,
    "acceleration": 84.62,
    "handling": 69.2,
    "nitro": 63.68,
    "n_top_speed": 0.5381850853548967,
    "n_acceleration": 0.9348210340256298,
    "n_handling": 0.6796974756900108,
    "n_nitro": 0.7371223521240884
  },
  {
    "id": "aston_martin_v12_speedster",
    "name": "Aston Martin V12 Speedster",
    "rank": 0,
    "car_class": "C",
    "top_speed": 313.0,
    "acceleration": 80.12,
    "handling": 57.28,
    "nitro": 62.51,
    "n_top_speed": 0.5624438454627134,
    "n_acceleration": 0.8851082633672117,
    "n_handling": 0.5626166388370494,
    "n_nitro": 0.7235791179534669
  },
  {
    "id": "donkervoort_d8_gto_individual_series",
    "name": "Donkervoort D8 GTO Individual Series",
    "rank": 0,
    "car_class": "C",
    "top_speed": 303.3,
    "acceleration": 85.43,
    "handling": 85.09,
    "nitro": 62.77,
    "n_top_speed": 0.5450134770889488,
    "n_acceleration": 0.9437693327441451,
    "n_handling": 0.8357725174344367,
    "n_nitro": 0.7265887255469383
  },
  {
    "id": "dodge_viper_acr",
    "name": "Dodge Viper ACR",
    "rank": 0,
    "car_class": "C",
    "top_speed": 303.9,
    "acceleration": 77.32,
    "handling": 86.2,
    "nitro": 68.94,
    "n_top_speed": 0.5460916442048517,
    "n_acceleration": 0.854175872735307,
    "n_handling": 0.8466751792554759,
    "n_nitro": 0.7980090288227804
  },
  {
    "id": "bolwell_mk_x_nagari_500",
    "name": "Bolwell MK X Nagari 500",
    "rank": 0,
    "car_class": "C",
    "top_speed": 314.6,
    "acceleration": 81.62,
    "handling": 65.85,
    "nitro": 62.99,
    "n_top_speed": 0.565318957771788,
    "n_acceleration": 0.9016791869200178,
    "n_handling": 0.6467930458697573,
    "n_nitro": 0.729135316587568
  },
  {
    "id": "ford_shelby_gr_1",
    "name": "Ford Shelby GR-1",
    "rank": 0,
    "car_class": "C",
    "top_speed": 321.7,
    "acceleration": 75.32,
    "handling": 69.6,
    "nitro": 66.63,
    "n_top_speed": 0.5780772686433063,
    "n_acceleration": 0.8320813079982324,
    "n_handling": 0.6836263628327276,
    "n_nitro": 0.7712698228961685
  },
  {
    "id": "pininfarina_h2_speed",
    "name": "Pininfarina H2 Speed",
    "rank": 0,
    "car_class": "C",
    "top_speed": 317.9,
    "acceleration": 78.22,
    "handling": 86.5,
    "nitro": 60.57,
    "n_top_speed": 0.5712488769092542,
    "n_acceleration": 0.8641184268669907,
    "n_handling": 0.8496218446125134,
    "n_nitro": 0.7011228151406412
  },
  {
    "id": "tvr_sagaris",
    "name": "TVR Sagaris",
    "rank": 0,
    "car_class": "C",
    "top_speed": 312.8,
    "acceleration": 75.52,
    "handling": 69.34,
    "nitro": 78.28,
    "n_top_speed": 0.5620844564240791,
    "n_acceleration": 0.83429076447194,
    "n_handling": 0.6810725861899617,
    "n_nitro": 0.9061233939113323
  },
  {
    "id": "artega_scalo_superelletra",
    "name": "Artega Scalo Superelletra",
    "rank": 0,
    "car_class": "C",
    "top_speed": 316.3,
    "acceleration": 85.72,
    "handling": 57.94,
    "nitro": 71.91,
    "n_top_speed": 0.5683737646001797,
    "n_acceleration": 0.9469730446310208,
    "n_handling": 0.5690993026225322,
    "n_nitro": 0.8323880078712813
  },
  {
    "id": "saleen_s1",
    "name": "Saleen S1",
    "rank": 0,
    "car_class": "C",
    "top_speed": 305.3,
    "acceleration": 76.74,
    "handling": 82.8,
    "nitro": 74.07,
    "n_top_speed": 0.548607367475292,
    "n_acceleration": 0.8477684489615555,
    "n_handling": 0.8132796385423828,
    "n_nitro": 0.8573909017247365
  },
  {
    "id": "acura_2017_nsx",
    "name": "Acura 2017 NSX",
    "rank": 0,
    "car_class": "C",
    "top_speed": 323.5,
    "acceleration": 84.32,
    "handling": 63.02,
    "nitro": 54.67,
    "n_top_speed": 0.5813117699910153,
    "n_acceleration": 0.9315068493150684,
    "n_handling": 0.6189961693350359,
    "n_nitro": 0.6328278735964811
  },
  {
    "id": "maserati_alfieri",
    "name": "Maserati Alfieri",
    "rank": 0,
    "car_class": "C",
    "top_speed": 335.7,
    "acceleration": 74.43,
    "handling": 41.38,
    "nitro": 72.91,
    "n_top_speed": 0.6032345013477088,
    "n_acceleration": 0.8222492266902344,
    "n_handling": 0.40644337491405563,
    "n_nitro": 0.8439634216923254
  },
  {
    "id": "porsche_mission_r",
    "name": "Porsche Mission R",
    "rank": 0,
    "car_class": "C",
    "top_speed": 312.1,
    "acceleration": 87.92,
    "handling": 63.47,
    "nitro": 62.72,
    "n_top_speed": 0.560826594788859,
    "n_acceleration": 0.971277065841803,
    "n_handling": 0.6234161673705922,
    "n_nitro": 0.726009954855886
  },
  {
    "id": "mercedes_benz_2022_showcar_vision_amg",
    "name": "Mercedes-Benz 2022 Showcar Vision AMG",
    "rank": 0,
    "car_class": "C",
    "top_speed": 334.7,
    "acceleration": 75.1,
    "handling": 51.51,
    "nitro": 58.86,
    "n_top_speed": 0.6014375561545373,
    "n_acceleration": 0.8296509058771542,
    "n_handling": 0.5059424418033591,
    "n_nitro": 0.6813288575066558
  },
  {
    "id": "ferrari_monza_sp1",
    "name": "Ferrari Monza Sp1",
    "rank": 0,
    "car_class": "C",
    "top_speed": 319.1,
    "acceleration": 82.32,
    "handling": 61.88,
    "nitro": 63.25,
    "n_top_speed": 0.5734052111410602,
    "n_acceleration": 0.9094122845779937,
    "n_handling": 0.607798840978293,
    "n_nitro": 0.7321449241810395
  },
  {
    "id": "ats_automobili_corsa_rrturbo",
    "name": "ATS Automobili Corsa Rrturbo",
    "rank": 0,
    "car_class": "C",
    "top_speed": 321.7,
    "acceleration": 87.51,
    "handling": 68.27,
    "nitro": 46.32,
    "n_top_speed": 0.5780772686433063,
    "n_acceleration": 0.9667476800707027,
    "n_handling": 0.6705628130831941,
    "n_nitro": 0.5361731681907628
  },
  {
    "id": "formula_e_gen_2_asphalt_edition",
    "name": "Formula E Gen 2 Asphalt Edition",
    "rank": 0,
    "car_class": "C",
    "top_speed": 304.6,
    "acceleration": 87.43,
    "handling": 83.66,
    "nitro": 75.04,
    "n_top_speed": 0.5473495058400719,
    "n_acceleration": 0.9658638974812197,
    "n_handling": 0.821726745899224,
    "n_nitro": 0.8686190531311495
  },
  {
    "id": "jaguar_xe_sv_project_8",
    "name": "Jaguar XE SV Project 8",
    "rank": 0,
    "car_class": "C",
    "top_speed": 338.7,
    "acceleration": 78.28,
    "handling": 48.14,
    "nitro": 62.98,
    "n_top_speed": 0.6086253369272236,
    "n_acceleration": 0.864781263809103,
    "n_handling": 0.47284156762596996,
    "n_nitro": 0.7290195624493575
  },
  {
    "id": "ferrari_f40",
    "name": "Ferrari F40",
    "rank": 0,
    "car_class": "C",
    "top_speed": 340.6,
    "acceleration": 72.88,
    "handling": 69.32,
    "nitro": 63.5,
    "n_top_speed": 0.6120395327942498,
    "n_acceleration": 0.8051259390190013,
    "n_handling": 0.6808761418328257,
    "n_nitro": 0.7350387776363005
  },
  {
    "id": "renault_r_s_01",
    "name": "Renault R.S. 01",
    "rank": 0,
    "car_class": "C",
    "top_speed": 320.7,
    "acceleration": 83.68,
    "handling": 61.38,
    "nitro": 72.01,
    "n_top_speed": 0.5762803234501348,
    "n_acceleration": 0.9244365885992047,
    "n_handling": 0.6028877320498969,
    "n_nitro": 0.8335455492533859
  },
  {
    "id": "mercedes_benz_clk_gtr",
    "name": "Mercedes-Benz CLK-GTR",
    "rank": 0,
    "car_class": "C",
    "top_speed": 332.7,
    "acceleration": 78.92,
    "handling": 68.01,
    "nitro": 57.24,
    "n_top_speed": 0.597843665768194,
    "n_acceleration": 0.871851524524967,
    "n_handling": 0.6680090364404283,
    "n_nitro": 0.6625766871165645
  },
  {
    "id": "acura_nsx_gt3_evo",
    "name": "Acura NSX GT3 Evo",
    "rank": 0,
    "car_class": "C",
    "top_speed": 314.4,
    "acceleration": 74.29,
    "handling": 86.13,
    "nitro": 73.76,
    "n_top_speed": 0.5649595687331536,
    "n_acceleration": 0.8207026071586391,
    "n_handling": 0.8459876240055004,
    "n_nitro": 0.853802523440213
  },
  {
    "id": "vencer_sarthe",
    "name": "Vencer Sarthe",
    "rank": 0,
    "car_class": "C",
    "top_speed": 350.5,
    "acceleration": 74.12,
    "handling": 62.87,
    "nitro": 46.83,
    "n_top_speed": 0.6298292902066487,
    "n_acceleration": 0.8188245691559877,
    "n_handling": 0.617522836656517,
    "n_nitro": 0.5420766292394953
  },
  {
    "id": "maserati_mc12",
    "name": "Maserati MC12",
    "rank": 0,
    "car_class": "C",
    "top_speed": 342.9,
    "acceleration": 76.48,
    "handling": 72.36,
    "nitro": 38.94,
    "n_top_speed": 0.6161725067385444,
    "n_acceleration": 0.8448961555457358,
    "n_handling": 0.7107356841174737,
    "n_nitro": 0.45074661419145734
  },
  {
    "id": "bentley_mulliner_bacalar",
    "name": "Bentley Mulliner Bacalar",
    "rank": 0,
    "car_class": "C",
    "top_speed": 340.4,
    "acceleration": 77.38,
    "handling": 67.26,
    "nitro": 55.86,
    "n_top_speed": 0.6116801437556154,
    "n_acceleration": 0.8548387096774194,
    "n_handling": 0.6606423730478342,
    "n_nitro": 0.6466026160435235
  },
  {
    "id": "de_tomaso_p900",
    "name": "DE Tomaso P900",
    "rank": 0,
    "car_class": "C",
    "top_speed": 335.2,
    "acceleration": 81.32,
    "handling": 60.44,
    "nitro": 59.52,
    "n_top_speed": 0.602336028751123,
    "n_acceleration": 0.8983650022094565,
    "n_handling": 0.5936548472645123,
    "n_nitro": 0.688968630628545
  },
  {
    "id": "lamborghini_miura_concept",
    "name": "Lamborghini Miura Concept",
    "rank": 0,
    "car_class": "C",
    "top_speed": 346.2,
    "acceleration": 72.32,
    "handling": 54.97,
    "nitro": 60.38,
    "n_top_speed": 0.6221024258760107,
    "n_acceleration": 0.7989394608926204,
    "n_handling": 0.5399273155878597,
    "n_nitro": 0.698923486514643
  },
  {
    "id": "porsche_718_cayman_gt4_clubsport",
    "name": "Porsche 718 Cayman Gt4 Clubsport",
    "rank": 0,
    "car_class": "C",
    "top_speed": 323.6,
    "acceleration": 73.44,
    "handling": 87.24,
    "nitro": 70.55,
    "n_top_speed": 0.5814914645103325,
    "n_acceleration": 0.8113124171453823,
    "n_handling": 0.8568902858265396,
    "n_nitro": 0.8166454450746614
  },
  {
    "id": "chevrolet_corvette_stingray",
    "name": "Chevrolet Corvette Stingray",
    "rank": 0,
    "car_class": "C",
    "top_speed": 327.7,
    "acceleration": 81.56,
    "handling": 60.15,
    "nitro": 64.44,
    "n_top_speed": 0.5888589398023361,
    "n_acceleration": 0.9010163499779055,
    "n_handling": 0.5908064040860426,
    "n_nitro": 0.745919666628082
  },
  {
    "id": "maserati_mc20_gt2",
    "name": "Maserati MC20 GT2",
    "rank": 0,
    "car_class": "C",
    "top_speed": 336.3,
    "acceleration": 83.68,
    "handling": 63.95,
    "nitro": 46.53,
    "n_top_speed": 0.6043126684636119,
    "n_acceleration": 0.9244365885992047,
    "n_handling": 0.6281308319418525,
    "n_nitro": 0.5386040050931821
  },
  {
    "id": "ferrari_599xx_evo",
    "name": "Ferrari 599XX Evo",
    "rank": 0,
    "car_class": "C",
    "top_speed": 322.0,
    "acceleration": 80.98,
    "handling": 83.65,
    "nitro": 70.81,
    "n_top_speed": 0.5786163522012578,
    "n_acceleration": 0.8946089262041539,
    "n_handling": 0.8216285237206562,
    "n_nitro": 0.8196550526681329
  },
  {
    "id": "lamborghini_diablo_gt",
    "name": "Lamborghini Diablo GT",
    "rank": 0,
    "car_class": "C",
    "top_speed": 348.6,
    "acceleration": 74.03,
    "handling": 62.5,
    "nitro": 58.63,
    "n_top_speed": 0.6264150943396227,
    "n_acceleration": 0.8178303137428193,
    "n_handling": 0.613888616049504,
    "n_nitro": 0.6786665123278157
  },
  {
    "id": "arrinera_hussarya_33",
    "name": "Arrinera Hussarya 33",
    "rank": 0,
    "car_class": "C",
    "top_speed": 352.1,
    "acceleration": 78.53,
    "handling": 59.47,
    "nitro": 47.71,
    "n_top_speed": 0.6327044025157234,
    "n_acceleration": 0.8675430844012374,
    "n_handling": 0.584127295943424,
    "n_nitro": 0.5522629934020141
  },
  {
    "id": "bugatti_eb110",
    "name": "Bugatti EB110",
    "rank": 0,
    "car_class": "C",
    "top_speed": 348.4,
    "acceleration": 74.12,
    "handling": 66.08,
    "nitro": 58.15,
    "n_top_speed": 0.6260557053009883,
    "n_acceleration": 0.8188245691559877,
    "n_handling": 0.6490521559768195,
    "n_nitro": 0.6731103136937145
  },
  {
    "id": "porsche_panamera_turbo_s",
    "name": "Porsche Panamera Turbo S",
    "rank": 0,
    "car_class": "C",
    "top_speed": 326.2,
    "acceleration": 88.03,
    "handling": 72.48,
    "nitro": 58.56,
    "n_top_speed": 0.5861635220125786,
    "n_acceleration": 0.972492266902342,
    "n_handling": 0.7119143502602888,
    "n_nitro": 0.6778562333603426
  },
  {
    "id": "lamborghini_gallardo_lp_560_4",
    "name": "Lamborghini Gallardo LP 560-4",
    "rank": 0,
    "car_class": "C",
    "top_speed": 340.7,
    "acceleration": 76.56,
    "handling": 75.81,
    "nitro": 59.69,
    "n_top_speed": 0.6122192273135669,
    "n_acceleration": 0.8457799381352188,
    "n_handling": 0.7446223357234063,
    "n_nitro": 0.6909364509781224
  },
  {
    "id": "ferrari_296_gtb",
    "name": "Ferrari 296 GTB",
    "rank": 0,
    "car_class": "C",
    "top_speed": 341.6,
    "acceleration": 81.23,
    "handling": 65.0,
    "nitro": 52.13,
    "n_top_speed": 0.6138364779874215,
    "n_acceleration": 0.8973707467962881,
    "n_handling": 0.6384441606914841,
    "n_nitro": 0.6034263224910291
  },
  {
    "id": "mclaren_gt",
    "name": "McLaren GT",
    "rank": 0,
    "car_class": "C",
    "top_speed": 339.1,
    "acceleration": 80.98,
    "handling": 69.09,
    "nitro": 57.31,
    "n_top_speed": 0.6093441150044924,
    "n_acceleration": 0.8946089262041539,
    "n_handling": 0.6786170317257637,
    "n_nitro": 0.6633869660840376
  },
  {
    "id": "mercedes_benz_mercedes_amg_gt_black_series",
    "name": "Mercedes-Benz Mercedes-AMG GT Black Series",
    "rank": 0,
    "car_class": "C",
    "top_speed": 335.7,
    "acceleration": 81.79,
    "handling": 60.83,
    "nitro": 65.62,
    "n_top_speed": 0.6032345013477088,
    "n_acceleration": 0.9035572249226691,
    "n_handling": 0.5974855122286612,
    "n_nitro": 0.759578654936914
  },
  {
    "id": "ferrari_daytona_sp3",
    "name": "Ferrari Daytona Sp3",
    "rank": 0,
    "car_class": "C",
    "top_speed": 348.8,
    "acceleration": 80.46,
    "handling": 54.89,
    "nitro": 60.3,
    "n_top_speed": 0.626774483378257,
    "n_acceleration": 0.8888643393725143,
    "n_handling": 0.5391415381593163,
    "n_nitro": 0.6979974534089594
  },
  {
    "id": "porsche_911_gts_coupe",
    "name": "Porsche 911 GTS Coupe",
    "rank": 0,
    "car_class": "B",
    "top_speed": 328.8,
    "acceleration": 71.21,
    "handling": 45.85,
    "nitro": 56.6,
    "n_top_speed": 0.5908355795148248,
    "n_acceleration": 0.7866769774635439,
    "n_handling": 0.45034868873391615,
    "n_nitro": 0.6551684222710962
  },
  {
    "id": "aston_martin_db11",
    "name": "Aston Martin DB11",
    "rank": 0,
    "car_class": "B",
    "top_speed": 340.6,
    "acceleration": 74.2,
    "handling": 43.21,
    "nitro": 55.4,
    "n_top_speed": 0.6120395327942498,
    "n_acceleration": 0.8197083517454706,
    "n_handling": 0.42441803359198504,
    "n_nitro": 0.6412779256858433
  },
  {
    "id": "jaguar_f_type_svr",
    "name": "Jaguar F-Type SVR",
    "rank": 0,
    "car_class": "B",
    "top_speed": 341.0,
    "acceleration": 75.55,
    "handling": 49.28,
    "nitro": 50.12,
    "n_top_speed": 0.6127583108715184,
    "n_acceleration": 0.8346221829429961,
    "n_handling": 0.4840388959827129,
    "n_nitro": 0.5801597407107304
  },
  {
    "id": "ferrari_f50",
    "name": "Ferrari F50",
    "rank": 0,
    "car_class": "B",
    "top_speed": 338.9,
    "acceleration": 73.85,
    "handling": 43.52,
    "nitro": 61.42,
    "n_top_speed": 0.608984725965858,
    "n_acceleration": 0.8158418029164826,
    "n_handling": 0.42746292112759066,
    "n_nitro": 0.7109619168885288
  },
  {
    "id": "exotic_rides_w70",
    "name": "Exotic Rides W70",
    "rank": 0,
    "car_class": "B",
    "top_speed": 329.7,
    "acceleration": 80.21,
    "handling": 45.2,
    "nitro": 56.71,
    "n_top_speed": 0.5924528301886792,
    "n_acceleration": 0.88610251878038,
    "n_handling": 0.4439642471270013,
    "n_nitro": 0.656441717791411
  },
  {
    "id": "porsche_911_gt1_evolution",
    "name": "Porsche 911 GT1 Evolution",
    "rank": 0,
    "car_class": "B",
    "top_speed": 329.8,
    "acceleration": 75.15,
    "handling": 53.7,
    "nitro": 68.88,
    "n_top_speed": 0.5926325247079964,
    "n_acceleration": 0.8302032699955811,
    "n_handling": 0.5274530989097338,
    "n_nitro": 0.7973145039935177
  },
  {
    "id": "ford_gt",
    "name": "Ford GT",
    "rank": 0,
    "car_class": "B",
    "top_speed": 362.8,
    "acceleration": 79.15,
    "handling": 34.36,
    "nitro": 54.49,
    "n_top_speed": 0.6519317160826595,
    "n_acceleration": 0.8743923994697306,
    "n_handling": 0.3374914055593753,
    "n_nitro": 0.6307442991086931
  },
  {
    "id": "lamborghini_asterion",
    "name": "Lamborghini Asterion",
    "rank": 0,
    "car_class": "B",
    "top_speed": 336.8,
    "acceleration": 81.05,
    "handling": 45.56,
    "nitro": 68.21,
    "n_top_speed": 0.6052111410601977,
    "n_acceleration": 0.8953822359699514,
    "n_handling": 0.44750024555544643,
    "n_nitro": 0.7895589767334181
  },
  {
    "id": "ford_mustang_rtr_spec_5_10th_anniversary",
    "name": "Ford Mustang RTR Spec 5 10th Anniversary",
    "rank": 0,
    "car_class": "B",
    "top_speed": 335.2,
    "acceleration": 75.65,
    "handling": 46.89,
    "nitro": 73.82,
    "n_top_speed": 0.602336028751123,
    "n_acceleration": 0.8357269111798499,
    "n_handling": 0.4605637953049799,
    "n_nitro": 0.8544970482694756
  },
  {
    "id": "ferrari_roma",
    "name": "Ferrari Roma",
    "rank": 0,
    "car_class": "B",
    "top_speed": 331.7,
    "acceleration": 77.45,
    "handling": 60.49,
    "nitro": 66.78,
    "n_top_speed": 0.5960467205750224,
    "n_acceleration": 0.8556120194432171,
    "n_handling": 0.5941459581573519,
    "n_nitro": 0.7730061349693251
  },
  {
    "id": "arash_af10",
    "name": "Arash AF10",
    "rank": 0,
    "car_class": "A",
    "top_speed": 337.0,
    "acceleration": 78.73,
    "handling": 50.41,
    "nitro": 59.6,
    "n_top_speed": 0.605570530098832,
    "n_acceleration": 0.8697525408749448,
    "n_handling": 0.4951380021608879,
    "n_nitro": 0.6898946637342285
  },
  {
    "id": "bmw_gt3",
    "name": "BMW GT3",
    "rank": 0,
    "car_class": "B",
    "top_speed": 333.3,
    "acceleration": 79.46,
    "handling": 53.36,
    "nitro": 63.69,
    "n_top_speed": 0.5989218328840971,
    "n_acceleration": 0.8778170570039769,
    "n_handling": 0.5241135448384245,
    "n_nitro": 0.7372381062622988
  },
  {
    "id": "cadillac_cien_concept",
    "name": "Cadillac Cien Concept",
    "rank": 0,
    "car_class": "B",
    "top_speed": 368.0,
    "acceleration": 76.55,
    "handling": 36.14,
    "nitro": 61.1,
    "n_top_speed": 0.6612758310871518,
    "n_acceleration": 0.8456694653115334,
    "n_handling": 0.35497495334446516,
    "n_nitro": 0.7072577844657947
  },
  {
    "id": "aston_martin_valour",
    "name": "Aston Martin Valour",
    "rank": 0,
    "car_class": "B",
    "top_speed": 331.0,
    "acceleration": 78.23,
    "handling": 56.43,
    "nitro": 60.73,
    "n_top_speed": 0.5947888589398024,
    "n_acceleration": 0.8642288996906762,
    "n_handling": 0.5542677536587761,
    "n_nitro": 0.7029748813520083
  },
  {
    "id": "ford_gt_mk_ii",
    "name": "Ford GT MK II",
    "rank": 0,
    "car_class": "B",
    "top_speed": 315.5,
    "acceleration": 86.26,
    "handling": 79.0,
    "nitro": 67.88,
    "n_top_speed": 0.5669362084456424,
    "n_acceleration": 0.952938577110031,
    "n_handling": 0.775955210686573,
    "n_nitro": 0.7857390901724736
  },
  {
    "id": "lamborghini_huracan_sto",
    "name": "Lamborghini Huracan STO",
    "rank": 0,
    "car_class": "B",
    "top_speed": 320.3,
    "acceleration": 85.88,
    "handling": 73.05,
    "nitro": 57.09,
    "n_top_speed": 0.5755615453728662,
    "n_acceleration": 0.9487406098099868,
    "n_handling": 0.7175130144386602,
    "n_nitro": 0.6608403750434079
  },
  {
    "id": "italdesign_zerouno",
    "name": "Italdesign Zerouno",
    "rank": 0,
    "car_class": "B",
    "top_speed": 341.0,
    "acceleration": 79.25,
    "handling": 58.34,
    "nitro": 54.1,
    "n_top_speed": 0.6127583108715184,
    "n_acceleration": 0.8754971277065842,
    "n_handling": 0.573028189765249,
    "n_nitro": 0.626229887718486
  },
  {
    "id": "mclaren_artura",
    "name": "McLaren Artura",
    "rank": 0,
    "car_class": "B",
    "top_speed": 337.7,
    "acceleration": 81.05,
    "handling": 68.33,
    "nitro": 47.34,
    "n_top_speed": 0.6068283917340521,
    "n_acceleration": 0.8953822359699514,
    "n_handling": 0.6711521461546017,
    "n_nitro": 0.5479800902882278
  },
  {
    "id": "arash_af8_falcon_edition",
    "name": "Arash AF8 Falcon Edition",
    "rank": 0,
    "car_class": "B",
    "top_speed": 332.6,
    "acceleration": 76.74,
    "handling": 66.01,
    "nitro": 76.94,
    "n_top_speed": 0.5976639712488769,
    "n_acceleration": 0.8477684489615555,
    "n_handling": 0.6483646007268442,
    "n_nitro": 0.8906123393911332
  },
  {
    "id": "ferrari_488_gtb",
    "name": "Ferrari 488 GTB",
    "rank": 0,
    "car_class": "B",
    "top_speed": 347.6,
    "acceleration": 80.24,
    "handling": 48.38,
    "nitro": 65.84,
    "n_top_speed": 0.6246181491464511,
    "n_acceleration": 0.8864339372514362,
    "n_handling": 0.4751988999116001,
    "n_nitro": 0.7621252459775437
  },
  {
    "id": "kepler_motion",
    "name": "Kepler Motion",
    "rank": 0,
    "car_class": "B",
    "top_speed": 338.5,
    "acceleration": 86.45,
    "handling": 48.72,
    "nitro": 61.18,
    "n_top_speed": 0.6082659478885895,
    "n_acceleration": 0.9550375607600531,
    "n_handling": 0.47853845398290934,
    "n_nitro": 0.7081838175714782
  },
  {
    "id": "drako_gte",
    "name": "Drako GTE",
    "rank": 0,
    "car_class": "B",
    "top_speed": 346.2,
    "acceleration": 81.85,
    "handling": 47.31,
    "nitro": 61.18,
    "n_top_speed": 0.6221024258760107,
    "n_acceleration": 0.9042200618647812,
    "n_handling": 0.46468912680483254,
    "n_nitro": 0.7081838175714782
  },
  {
    "id": "glickenhaus_003s",
    "name": "Glickenhaus 003S",
    "rank": 0,
    "car_class": "B",
    "top_speed": 368.8,
    "acceleration": 79.44,
    "handling": 38.58,
    "nitro": 63.11,
    "n_top_speed": 0.6627133872416892,
    "n_acceleration": 0.8775961113566063,
    "n_handling": 0.37894116491503776,
    "n_nitro": 0.7305243662460933
  },
  {
    "id": "mclaren_elva",
    "name": "McLaren Elva",
    "rank": 0,
    "car_class": "B",
    "top_speed": 339.1,
    "acceleration": 81.31,
    "handling": 75.51,
    "nitro": 65.9,
    "n_top_speed": 0.6093441150044924,
    "n_acceleration": 0.8982545293857712,
    "n_handling": 0.7416756703663687,
    "n_nitro": 0.7628197708068064
  },
  {
    "id": "aston_martin_db12",
    "name": "Aston Martin DB12",
    "rank": 0,
    "car_class": "B",
    "top_speed": 343.2,
    "acceleration": 74.11,
    "handling": 69.68,
    "nitro": 77.89,
    "n_top_speed": 0.6167115902964959,
    "n_acceleration": 0.8187140963323023,
    "n_handling": 0.6844121402612711,
    "n_nitro": 0.9016089825211251
  },
  {
    "id": "nissan_r390_gt1",
    "name": "Nissan R390 GT1",
    "rank": 0,
    "car_class": "B",
    "top_speed": 373.5,
    "acceleration": 76.72,
    "handling": 52.63,
    "nitro": 55.45,
    "n_top_speed": 0.6711590296495957,
    "n_acceleration": 0.8475475033141847,
    "n_handling": 0.5169433258029663,
    "n_nitro": 0.6418566963768955
  },
  {
    "id": "ferrari_f12tdf",
    "name": "Ferrari F12tdf",
    "rank": 0,
    "car_class": "B",
    "top_speed": 360.5,
    "acceleration": 78.38,
    "handling": 40.13,
    "nitro": 80.18,
    "n_top_speed": 0.6477987421383647,
    "n_acceleration": 0.8658859920459567,
    "n_handling": 0.39416560259306554,
    "n_nitro": 0.9281166801713162
  },
  {
    "id": "maserati_mc20",
    "name": "Maserati MC20",
    "rank": 0,
    "car_class": "B",
    "top_speed": 335.7,
    "acceleration": 81.63,
    "handling": 90.79,
    "nitro": 75.84,
    "n_top_speed": 0.6032345013477088,
    "n_acceleration": 0.9017896597437031,
    "n_handling": 0.8917591592181515,
    "n_nitro": 0.8778793841879847
  },
  {
    "id": "lamborghini_murcielago_lp_640_roadster",
    "name": "Lamborghini Murcielago LP 640 Roadster",
    "rank": 0,
    "car_class": "B",
    "top_speed": 354.1,
    "acceleration": 77.54,
    "handling": 67.18,
    "nitro": 61.13,
    "n_top_speed": 0.6362982929020665,
    "n_acceleration": 0.8566062748563854,
    "n_handling": 0.6598565956192909,
    "n_nitro": 0.707605046880426
  },
  {
    "id": "mclaren_765lt",
    "name": "McLaren 765LT",
    "rank": 0,
    "car_class": "B",
    "top_speed": 349.5,
    "acceleration": 80.5,
    "handling": 70.61,
    "nitro": 62.26,
    "n_top_speed": 0.628032345013477,
    "n_acceleration": 0.8893062306672559,
    "n_handling": 0.6935468028680876,
    "n_nitro": 0.7206852644982058
  },
  {
    "id": "chevrolet_corvette_grand_sport",
    "name": "Chevrolet Corvette Grand Sport",
    "rank": 0,
    "car_class": "B",
    "top_speed": 331.2,
    "acceleration": 76.55,
    "handling": 92.99,
    "nitro": 80.87,
    "n_top_speed": 0.5951482479784367,
    "n_acceleration": 0.8456694653115334,
    "n_handling": 0.9133680385030939,
    "n_nitro": 0.9361037157078366
  },
  {
    "id": "aston_martin_vantage_gt12",
    "name": "Aston Martin Vantage GT12",
    "rank": 0,
    "car_class": "B",
    "top_speed": 337.8,
    "acceleration": 78.26,
    "handling": 86.85,
    "nitro": 80.46,
    "n_top_speed": 0.6070080862533693,
    "n_acceleration": 0.8645603181617323,
    "n_handling": 0.8530596208623906,
    "n_nitro": 0.9313577960412084
  },
  {
    "id": "apex_ap_0",
    "name": "Apex AP-0",
    "rank": 0,
    "car_class": "B",
    "top_speed": 335.1,
    "acceleration": 80.96,
    "handling": 89.37,
    "nitro": 75.16,
    "n_top_speed": 0.6021563342318059,
    "n_acceleration": 0.894387980556783,
    "n_handling": 0.8778116098615067,
    "n_nitro": 0.8700081027896747
  },
  {
    "id": "apollo_ie",
    "name": "Apollo IE",
    "rank": 0,
    "car_class": "B",
    "top_speed": 348.3,
    "acceleration": 84.65,
    "handling": 73.17,
    "nitro": 69.12,
    "n_top_speed": 0.6258760107816712,
    "n_acceleration": 0.9351524524966859,
    "n_handling": 0.7186916805814753,
    "n_nitro": 0.8000926033105684
  },
  {
    "id": "sin_r1_550",
    "name": "SIN R1 550",
    "rank": 0,
    "car_class": "B",
    "top_speed": 370.6,
    "acceleration": 77.04,
    "handling": 45.74,
    "nitro": 85.0,
    "n_top_speed": 0.665947888589398,
    "n_acceleration": 0.8510826336721168,
    "n_handling": 0.449268244769669,
    "n_nitro": 0.9839101747887486
  },
  {
    "id": "lamborghini_reventon_roadster",
    "name": "Lamborghini Reventon Roadster",
    "rank": 0,
    "car_class": "B",
    "top_speed": 356.3,
    "acceleration": 78.35,
    "handling": 67.65,
    "nitro": 74.41,
    "n_top_speed": 0.640251572327044,
    "n_acceleration": 0.8655545735749005,
    "n_handling": 0.6644730380119831,
    "n_nitro": 0.8613265424238916
  },
  {
    "id": "ferrari_enzo_ferrari",
    "name": "Ferrari Enzo Ferrari",
    "rank": 0,
    "car_class": "B",
    "top_speed": 364.8,
    "acceleration": 75.29,
    "handling": 64.95,
    "nitro": 72.26,
    "n_top_speed": 0.6555256064690027,
    "n_acceleration": 0.8317498895271764,
    "n_handling": 0.6379530497986445,
    "n_nitro": 0.8364394027086469
  },
  {
    "id": "aston_martin_one77",
    "name": "Aston Martin One77",
    "rank": 0,
    "car_class": "B",
    "top_speed": 363.5,
    "acceleration": 79.34,
    "handling": 68.7,
    "nitro": 56.61,
    "n_top_speed": 0.6531895777178796,
    "n_acceleration": 0.8764913831197526,
    "n_handling": 0.6747863667616147,
    "n_nitro": 0.6552841764093066
  },
  {
    "id": "apollo_n",
    "name": "Apollo N",
    "rank": 0,
    "car_class": "B",
    "top_speed": 374.1,
    "acceleration": 80.32,
    "handling": 58.13,
    "nitro": 60.57,
    "n_top_speed": 0.6722371967654986,
    "n_acceleration": 0.8873177198409191,
    "n_handling": 0.5709655240153226,
    "n_nitro": 0.7011228151406412
  },
  {
    "id": "mercedes_benz_slr_mclaren",
    "name": "Mercedes-Benz SLR McLaren",
    "rank": 0,
    "car_class": "B",
    "top_speed": 353.3,
    "acceleration": 78.18,
    "handling": 66.6,
    "nitro": 79.54,
    "n_top_speed": 0.6348607367475292,
    "n_acceleration": 0.8636765355722493,
    "n_handling": 0.6541597092623513,
    "n_nitro": 0.920708415325848
  },
  {
    "id": "aston_martin_dbs_superleggera",
    "name": "Aston Martin DBS Superleggera",
    "rank": 0,
    "car_class": "B",
    "top_speed": 355.4,
    "acceleration": 79.16,
    "handling": 70.74,
    "nitro": 73.88,
    "n_top_speed": 0.6386343216531896,
    "n_acceleration": 0.8745028722934158,
    "n_handling": 0.6948236911894705,
    "n_nitro": 0.8551915730987382
  },
  {
    "id": "lamborghini_essenza_scv12",
    "name": "Lamborghini Essenza SCV12",
    "rank": 0,
    "car_class": "B",
    "top_speed": 340.8,
    "acceleration": 85.1,
    "handling": 75.84,
    "nitro": 74.27,
    "n_top_speed": 0.6123989218328841,
    "n_acceleration": 0.9401237295625275,
    "n_handling": 0.7449170022591102,
    "n_nitro": 0.8597059844889454
  },
  {
    "id": "lamborghini_sc63",
    "name": "Lamborghini SC63",
    "rank": 0,
    "car_class": "B",
    "top_speed": 353.8,
    "acceleration": 85.38,
    "handling": 70.15,
    "nitro": 56.43,
    "n_top_speed": 0.635759209344115,
    "n_acceleration": 0.943216968625718,
    "n_handling": 0.6890285826539633,
    "n_nitro": 0.6532006019215187
  },
  {
    "id": "mclaren_600lt_spider",
    "name": "Mclaren 600LT Spider",
    "rank": 0,
    "car_class": "B",
    "top_speed": 340.5,
    "acceleration": 86.11,
    "handling": 83.17,
    "nitro": 74.54,
    "n_top_speed": 0.6118598382749326,
    "n_acceleration": 0.9512814847547504,
    "n_handling": 0.816913859149396,
    "n_nitro": 0.8628313462206274
  },
  {
    "id": "puritalia_berlinetta",
    "name": "Puritalia Berlinetta",
    "rank": 0,
    "car_class": "B",
    "top_speed": 349.5,
    "acceleration": 83.43,
    "handling": 82.74,
    "nitro": 69.66,
    "n_top_speed": 0.628032345013477,
    "n_acceleration": 0.9216747680070704,
    "n_handling": 0.8126903054709753,
    "n_nitro": 0.8063433267739322
  },
  {
    "id": "mclaren_solus_gt",
    "name": "McLaren Solus GT",
    "rank": 0,
    "car_class": "B",
    "top_speed": 335.4,
    "acceleration": 89.3,
    "handling": 83.12,
    "nitro": 76.83,
    "n_top_speed": 0.6026954177897573,
    "n_acceleration": 0.9865223155103845,
    "n_handling": 0.8164227482565564,
    "n_nitro": 0.8893390438708183
  },
  {
    "id": "lamborghini_invencible",
    "name": "Lamborghini Invencible",
    "rank": 0,
    "car_class": "B",
    "top_speed": 340.4,
    "acceleration": 88.49,
    "handling": 75.74,
    "nitro": 67.64,
    "n_top_speed": 0.6116801437556154,
    "n_acceleration": 0.9775740167918692,
    "n_handling": 0.7439347804734309,
    "n_nitro": 0.782960990855423
  },
  {
    "id": "lamborghini_huracan_evo_spyder",
    "name": "Lamborghini Huracan Evo Spyder",
    "rank": 0,
    "car_class": "B",
    "top_speed": 344.0,
    "acceleration": 84.31,
    "handling": 75.97,
    "nitro": 82.43,
    "n_top_speed": 0.6181491464510332,
    "n_acceleration": 0.9313963764913832,
    "n_handling": 0.746193890580493,
    "n_nitro": 0.9541613612686655
  },
  {
    "id": "porsche_carrera_gt",
    "name": "Porsche Carrera GT",
    "rank": 0,
    "car_class": "B",
    "top_speed": 347.8,
    "acceleration": 78.67,
    "handling": 84.88,
    "nitro": 82.91,
    "n_top_speed": 0.6249775381850854,
    "n_acceleration": 0.8690897039328326,
    "n_handling": 0.8337098516845103,
    "n_nitro": 0.9597175599027665
  },
  {
    "id": "nissan_gtr_50_italdesign",
    "name": "Nissan GTR-50 Italdesign",
    "rank": 0,
    "car_class": "B",
    "top_speed": 349.5,
    "acceleration": 86.36,
    "handling": 73.86,
    "nitro": 64.59,
    "n_top_speed": 0.628032345013477,
    "n_acceleration": 0.9540433053468848,
    "n_handling": 0.7254690109026618,
    "n_nitro": 0.7476559787012386
  },
  {
    "id": "zenvo_tsr_s",
    "name": "Zenvo TSR-S",
    "rank": 0,
    "car_class": "B",
    "top_speed": 342.4,
    "acceleration": 85.38,
    "handling": 82.88,
    "nitro": 67.36,
    "n_top_speed": 0.6152740341419586,
    "n_acceleration": 0.943216968625718,
    "n_handling": 0.8140654159709262,
    "n_nitro": 0.7797198749855307
  },
  {
    "id": "lamborghini_sesto_elemento",
    "name": "Lamborghini Sesto Elemento",
    "rank": 0,
    "car_class": "B",
    "top_speed": 346.5,
    "acceleration": 87.26,
    "handling": 70.27,
    "nitro": 74.76,
    "n_top_speed": 0.6226415094339622,
    "n_acceleration": 0.9639858594785684,
    "n_handling": 0.6902072487967783,
    "n_nitro": 0.8653779372612571
  },
  {
    "id": "porsche_911_gt3_rs",
    "name": "Porsche 911 GT3 RS",
    "rank": 0,
    "car_class": "B",
    "top_speed": 339.4,
    "acceleration": 85.84,
    "handling": 92.97,
    "nitro": 86.39,
    "n_top_speed": 0.6098831985624438,
    "n_acceleration": 0.9482987185152453,
    "n_handling": 0.9131715941459582,
    "n_nitro": 1.0
  },
  {
    "id": "ferrari_488_challenge_evo",
    "name": "Ferrari 488 Challenge Evo",
    "rank": 0,
    "car_class": "B",
    "top_speed": 351.2,
    "acceleration": 82.76,
    "handling": 77.11,
    "nitro": 76.98,
    "n_top_speed": 0.6310871518418688,
    "n_acceleration": 0.9142730888201503,
    "n_handling": 0.757391218937236,
    "n_nitro": 0.891075355943975
  },
  {
    "id": "apollo_evo",
    "name": "Apollo Evo",
    "rank": 0,
    "car_class": "B",
    "top_speed": 355.0,
    "acceleration": 85.46,
    "handling": 70.34,
    "nitro": 65.79,
    "n_top_speed": 0.637915543575921,
    "n_acceleration": 0.944100751215201,
    "n_handling": 0.6908948040467537,
    "n_nitro": 0.7615464752864916
  },
  {
    "id": "lotus_evija",
    "name": "Lotus Evija",
    "rank": 0,
    "car_class": "B",
    "top_speed": 368.1,
    "acceleration": 81.14,
    "handling": 65.02,
    "nitro": 63.31,
    "n_top_speed": 0.661455525606469,
    "n_acceleration": 0.8963764913831198,
    "n_handling": 0.63864060504862,
    "n_nitro": 0.7328394490103022
  },
  {
    "id": "mclaren_f1lm",
    "name": "McLaren F1LM",
    "rank": 0,
    "car_class": "B",
    "top_speed": 377.6,
    "acceleration": 74.66,
    "handling": 66.1,
    "nitro": 73.12,
    "n_top_speed": 0.6785265049415993,
    "n_acceleration": 0.8247901016349978,
    "n_handling": 0.6492486003339554,
    "n_nitro": 0.8463942585947448
  },
  {
    "id": "volksawagen_w12_coupe",
    "name": "Volksawagen W12 Coupe",
    "rank": 0,
    "car_class": "B",
    "top_speed": 370.5,
    "acceleration": 79.08,
    "handling": 84.44,
    "nitro": 54.64,
    "n_top_speed": 0.6657681940700808,
    "n_acceleration": 0.8736190897039329,
    "n_handling": 0.8293880758275218,
    "n_nitro": 0.6324806111818497
  },
  {
    "id": "pagani_huayra_r",
    "name": "Pagani Huayra R",
    "rank": 0,
    "car_class": "B",
    "top_speed": 376.6,
    "acceleration": 83.17,
    "handling": 58.41,
    "nitro": 64.38,
    "n_top_speed": 0.6767295597484277,
    "n_acceleration": 0.9188024745912506,
    "n_handling": 0.5737157450152244,
    "n_nitro": 0.7452251417988193
  },
  {
    "id": "lamborghini_revuelto",
    "name": "Lamborghini Revuelto",
    "rank": 0,
    "car_class": "B",
    "top_speed": 361.5,
    "acceleration": 86.36,
    "handling": 76.33,
    "nitro": 54.22,
    "n_top_speed": 0.6495956873315364,
    "n_acceleration": 0.9540433053468848,
    "n_handling": 0.7497298890089382,
    "n_nitro": 0.6276189373770112
  },
  {
    "id": "lamborghini_temerario",
    "name": "Lamborghini Temerario",
    "rank": 0,
    "car_class": "B",
    "top_speed": 359.1,
    "acceleration": 87.26,
    "handling": 71.33,
    "nitro": 62.7,
    "n_top_speed": 0.6452830188679246,
    "n_acceleration": 0.9639858594785684,
    "n_handling": 0.7006187997249779,
    "n_nitro": 0.7257784465794652
  },
  {
    "id": "lotus_e_r9",
    "name": "Lotus E-R9",
    "rank": 0,
    "car_class": "B",
    "top_speed": 365.2,
    "acceleration": 87.44,
    "handling": 68.4,
    "nitro": 51.8,
    "n_top_speed": 0.6562443845462713,
    "n_acceleration": 0.965974370304905,
    "n_handling": 0.6718397014045772,
    "n_nitro": 0.5996064359300844
  },
  {
    "id": "aston_martin_vulcan",
    "name": "Aston Martin Vulcan",
    "rank": 0,
    "car_class": "A",
    "top_speed": 343.5,
    "acceleration": 78.7,
    "handling": 47.8,
    "nitro": 64.79,
    "n_top_speed": 0.6172506738544474,
    "n_acceleration": 0.8694211224038887,
    "n_handling": 0.4695020135546606,
    "n_nitro": 0.7499710614654475
  },
  {
    "id": "nissan_gt_r_nismo",
    "name": "Nissan GT-R Nismo",
    "rank": 0,
    "car_class": "A",
    "top_speed": 315.0,
    "acceleration": 77.5,
    "handling": 48.8,
    "nitro": 43.24,
    "n_top_speed": 0.5660377358490566,
    "n_acceleration": 0.8561643835616439,
    "n_handling": 0.4793242314114527,
    "n_nitro": 0.500520893621947
  },
  {
    "id": "nio_ep9",
    "name": "Nio EP9",
    "rank": 0,
    "car_class": "A",
    "top_speed": 313.0,
    "acceleration": 75.7,
    "handling": 52.47,
    "nitro": 49.64,
    "n_top_speed": 0.5624438454627134,
    "n_acceleration": 0.8362792752982767,
    "n_handling": 0.5153717709458796,
    "n_nitro": 0.5746035420766292
  },
  {
    "id": "ferrari_j50",
    "name": "Ferrari J50",
    "rank": 0,
    "car_class": "A",
    "top_speed": 333.0,
    "acceleration": 73.9,
    "handling": 42.27,
    "nitro": 48.91,
    "n_top_speed": 0.5983827493261455,
    "n_acceleration": 0.8163941670349095,
    "n_handling": 0.41518514880660057,
    "n_nitro": 0.566153489987267
  },
  {
    "id": "dodge_viper_gts",
    "name": "Dodge Viper GTS",
    "rank": 0,
    "car_class": "A",
    "top_speed": 340.0,
    "acceleration": 73.0,
    "handling": 40.65,
    "nitro": 56.62,
    "n_top_speed": 0.6109613656783468,
    "n_acceleration": 0.8064516129032259,
    "n_handling": 0.39927315587859735,
    "n_nitro": 0.655399930547517
  },
  {
    "id": "bentley_continental_gt_speed",
    "name": "Bentley Continental GT Speed",
    "rank": 0,
    "car_class": "A",
    "top_speed": 335.0,
    "acceleration": 67.6,
    "handling": 58.75,
    "nitro": 45.17,
    "n_top_speed": 0.6019766397124887,
    "n_acceleration": 0.7467962881131242,
    "n_handling": 0.5770552990865337,
    "n_nitro": 0.5228614422965622
  },
  {
    "id": "ferrari_laferrari",
    "name": "Ferrari Laferrari",
    "rank": 0,
    "car_class": "A",
    "top_speed": 350.0,
    "acceleration": 73.0,
    "handling": 37.68,
    "nitro": 62.91,
    "n_top_speed": 0.6289308176100629,
    "n_acceleration": 0.8064516129032259,
    "n_handling": 0.37010116884392497,
    "n_nitro": 0.7282092834818844
  },
  {
    "id": "mclaren_p1",
    "name": "Mclaren P1",
    "rank": 0,
    "car_class": "A",
    "top_speed": 350.0,
    "acceleration": 74.8,
    "handling": 39.97,
    "nitro": 53.74,
    "n_top_speed": 0.6289308176100629,
    "n_acceleration": 0.8263367211665931,
    "n_handling": 0.3925940477359788,
    "n_nitro": 0.6220627387429101
  },
  {
    "id": "pagani_zonda_hp_barchetta",
    "name": "Pagani Zonda HP Barchetta",
    "rank": 0,
    "car_class": "A",
    "top_speed": 338.0,
    "acceleration": 73.0,
    "handling": 51.67,
    "nitro": 59.37,
    "n_top_speed": 0.6073674752920036,
    "n_acceleration": 0.8064516129032259,
    "n_handling": 0.5075139966604459,
    "n_nitro": 0.6872323185553884
  },
  {
    "id": "lamborghini_aventadaor_sv_coupe",
    "name": "Lamborghini Aventadaor SV Coupe",
    "rank": 0,
    "car_class": "A",
    "top_speed": 350.0,
    "acceleration": 74.8,
    "handling": 41.5,
    "nitro": 59.86,
    "n_top_speed": 0.6289308176100629,
    "n_acceleration": 0.8263367211665931,
    "n_handling": 0.4076220410568706,
    "n_nitro": 0.6929042713276999
  },
  {
    "id": "mcmurtry_speirling",
    "name": "McMurtry Speirling",
    "rank": 0,
    "car_class": "A",
    "top_speed": 331.7,
    "acceleration": 90.52,
    "handling": 80.62,
    "nitro": 61.7,
    "n_top_speed": 0.5960467205750224,
    "n_acceleration": 1.0,
    "n_handling": 0.7918672036145762,
    "n_nitro": 0.7142030327584211
  },
  {
    "id": "ferrari_812_superfast",
    "name": "Ferrari 812 Superfast",
    "rank": 0,
    "car_class": "A",
    "top_speed": 340.0,
    "acceleration": 73.9,
    "handling": 46.64,
    "nitro": 60.62,
    "n_top_speed": 0.6109613656783468,
    "n_acceleration": 0.8163941670349095,
    "n_handling": 0.45810824084078183,
    "n_nitro": 0.7017015858316934
  },
  {
    "id": "lego_technic_mclaren_senna_gtr",
    "name": "Lego Technic Mclaren Senna GTR",
    "rank": 0,
    "car_class": "A",
    "top_speed": 335.0,
    "acceleration": 74.8,
    "handling": 57.64,
    "nitro": 49.12,
    "n_top_speed": 0.6019766397124887,
    "n_acceleration": 0.8263367211665931,
    "n_handling": 0.5661526372654946,
    "n_nitro": 0.5685843268896863
  },
  {
    "id": "chevrolet_corvette_zr1",
    "name": "Chevrolet Corvette ZR1",
    "rank": 0,
    "car_class": "A",
    "top_speed": 341.0,
    "acceleration": 74.8,
    "handling": 48.24,
    "nitro": 59.75,
    "n_top_speed": 0.6127583108715184,
    "n_acceleration": 0.8263367211665931,
    "n_handling": 0.47382378941164915,
    "n_nitro": 0.6916309758073851
  },
  {
    "id": "jaguar_c_x75",
    "name": "Jaguar C-X75",
    "rank": 0,
    "car_class": "A",
    "top_speed": 369.2,
    "acceleration": 75.54,
    "handling": 73.17,
    "nitro": 74.12,
    "n_top_speed": 0.6634321653189578,
    "n_acceleration": 0.8345117101193108,
    "n_handling": 0.7186916805814753,
    "n_nitro": 0.8579696724157889
  },
  {
    "id": "lego_technic_aston_martin_valkyrie",
    "name": "Lego Technic Aston Martin Valkyrie",
    "rank": 0,
    "car_class": "A",
    "top_speed": 350.0,
    "acceleration": 73.9,
    "handling": 43.04,
    "nitro": 60.87,
    "n_top_speed": 0.6289308176100629,
    "n_acceleration": 0.8163941670349095,
    "n_handling": 0.4227482565563304,
    "n_nitro": 0.7045954392869545
  },
  {
    "id": "vlf_force_1_v10",
    "name": "VLF Force 1 V10",
    "rank": 0,
    "car_class": "A",
    "top_speed": 350.0,
    "acceleration": 73.9,
    "handling": 43.04,
    "nitro": 60.87,
    "n_top_speed": 0.6289308176100629,
    "n_acceleration": 0.8163941670349095,
    "n_handling": 0.4227482565563304,
    "n_nitro": 0.7045954392869545
  },
  {
    "id": "ford_gt_frankie_edition",
    "name": "Ford GT Frankie Edition",
    "rank": 0,
    "car_class": "A",
    "top_speed": 371.8,
    "acceleration": 79.14,
    "handling": 58.82,
    "nitro": 74.63,
    "n_top_speed": 0.668104222821204,
    "n_acceleration": 0.8742819266460451,
    "n_handling": 0.5777428543365092,
    "n_nitro": 0.8638731334645213
  },
  {
    "id": "mclaren_senna_gtr",
    "name": "McLaren Senna GTR",
    "rank": 0,
    "car_class": "A",
    "top_speed": 358.0,
    "acceleration": 82.03,
    "handling": 60.84,
    "nitro": 77.62,
    "n_top_speed": 0.6433063791554358,
    "n_acceleration": 0.906208572691118,
    "n_handling": 0.5975837344072292,
    "n_nitro": 0.8984836207894432
  },
  {
    "id": "lamborghini_aventador_svj_roadster",
    "name": "Lamborghini Aventador SVJ Roadster",
    "rank": 0,
    "car_class": "A",
    "top_speed": 351.0,
    "acceleration": 73.9,
    "handling": 40.83,
    "nitro": 42.62,
    "n_top_speed": 0.6307277628032345,
    "n_acceleration": 0.8163941670349095,
    "n_handling": 0.40104115509281996,
    "n_nitro": 0.4933441370528996
  },
  {
    "id": "porsche_918_spyder",
    "name": "Porsche 918 Spyder",
    "rank": 0,
    "car_class": "A",
    "top_speed": 345.0,
    "acceleration": 76.59,
    "handling": 41.83,
    "nitro": 66.3,
    "n_top_speed": 0.6199460916442049,
    "n_acceleration": 0.8461113566062749,
    "n_handling": 0.410863372949612,
    "n_nitro": 0.767449936335224
  },
  {
    "id": "vanda_electrics_dendrobrium",
    "name": "Vanda Electrics Dendrobrium",
    "rank": 0,
    "car_class": "A",
    "top_speed": 339.9,
    "acceleration": 86.24,
    "handling": 95.92,
    "nitro": 84.9,
    "n_top_speed": 0.6107816711590296,
    "n_acceleration": 0.9527176314626602,
    "n_handling": 0.9421471368234947,
    "n_nitro": 0.9827526334066443
  },
  {
    "id": "peugeot_9x8",
    "name": "Peugeot 9x8",
    "rank": 0,
    "car_class": "A",
    "top_speed": 330.0,
    "acceleration": 82.0,
    "handling": 61.79,
    "nitro": 48.59,
    "n_top_speed": 0.5929919137466307,
    "n_acceleration": 0.9058771542200619,
    "n_handling": 0.6069148413711816,
    "n_nitro": 0.562449357564533
  },
  {
    "id": "aston_martin_dbs_gt_zagato",
    "name": "Aston Martin DBS GT Zagato",
    "rank": 0,
    "car_class": "A",
    "top_speed": 361.9,
    "acceleration": 80.65,
    "handling": 75.77,
    "nitro": 78.17,
    "n_top_speed": 0.650314465408805,
    "n_acceleration": 0.8909633230225366,
    "n_handling": 0.7442294470091346,
    "n_nitro": 0.9048500983910175
  },
  {
    "id": "mclaren_570s_spider",
    "name": "McLaren 570S Spider",
    "rank": 0,
    "car_class": "A",
    "top_speed": 377.2,
    "acceleration": 79.23,
    "handling": 66.06,
    "nitro": 64.75,
    "n_top_speed": 0.6778077268643307,
    "n_acceleration": 0.8752761820592135,
    "n_handling": 0.6488557116196837,
    "n_nitro": 0.7495080449126056
  },
  {
    "id": "automobili_pininfarina_battista_edizone_nino_farina",
    "name": "Automobili Pininfarina Battista Edizone Nino Farina",
    "rank": 0,
    "car_class": "S",
    "top_speed": 368.5,
    "acceleration": 88.49,
    "handling": 80.45,
    "nitro": 78.26,
    "n_top_speed": 0.6621743036837376,
    "n_acceleration": 0.9775740167918692,
    "n_handling": 0.7901974265789216,
    "n_nitro": 0.9058918856349115
  },
  {
    "id": "lamborghini_aventador_j",
    "name": "Lamborghini Aventador J",
    "rank": 0,
    "car_class": "A",
    "top_speed": 363.8,
    "acceleration": 79.83,
    "handling": 73.1,
    "nitro": 77.86,
    "n_top_speed": 0.6537286612758311,
    "n_acceleration": 0.8819045514803359,
    "n_handling": 0.7180041253314998,
    "n_nitro": 0.9012617201064937
  },
  {
    "id": "peugeot_onyx",
    "name": "Peugeot Onyx",
    "rank": 0,
    "car_class": "A",
    "top_speed": 360.0,
    "acceleration": 73.9,
    "handling": 63.83,
    "nitro": 35.08,
    "n_top_speed": 0.6469002695417789,
    "n_acceleration": 0.8163941670349095,
    "n_handling": 0.6269521657990373,
    "n_nitro": 0.4060655168422271
  },
  {
    "id": "glickenhaus_007s",
    "name": "Glickenhaus 007S",
    "rank": 0,
    "car_class": "A",
    "top_speed": 358.6,
    "acceleration": 89.33,
    "handling": 82.63,
    "nitro": 55.24,
    "n_top_speed": 0.6443845462713388,
    "n_acceleration": 0.9868537339814406,
    "n_handling": 0.8116098615067282,
    "n_nitro": 0.6394258594744763
  },
  {
    "id": "citroen_gt_by_citroen",
    "name": "Citroen GT by Citroen",
    "rank": 0,
    "car_class": "A",
    "top_speed": 388.7,
    "acceleration": 76.53,
    "handling": 64.61,
    "nitro": 67.2,
    "n_top_speed": 0.6984725965858041,
    "n_acceleration": 0.8454485196641627,
    "n_handling": 0.6346134957273352,
    "n_nitro": 0.7778678087741637
  },
  {
    "id": "porsche_935_2019",
    "name": "Porsche 935 (2019)",
    "rank": 0,
    "car_class": "A",
    "top_speed": 352.0,
    "acceleration": 84.94,
    "handling": 87.96,
    "nitro": 72.61,
    "n_top_speed": 0.6325247079964061,
    "n_acceleration": 0.9383561643835616,
    "n_handling": 0.8639622826834298,
    "n_nitro": 0.8404907975460123
  },
  {
    "id": "aston_martin_victor",
    "name": "Aston Martin Victor",
    "rank": 0,
    "car_class": "A",
    "top_speed": 371.4,
    "acceleration": 78.33,
    "handling": 76.84,
    "nitro": 69.63,
    "n_top_speed": 0.6673854447439352,
    "n_acceleration": 0.8653336279275299,
    "n_handling": 0.7547392201159022,
    "n_nitro": 0.8059960643593008
  },
  {
    "id": "porsche_911_gt2_rs_clubsport",
    "name": "Porsche 911 GT2 RS Clubsport",
    "rank": 0,
    "car_class": "A",
    "top_speed": 356.9,
    "acceleration": 83.64,
    "handling": 85.42,
    "nitro": 73.65,
    "n_top_speed": 0.6413297394429469,
    "n_acceleration": 0.9239946973044632,
    "n_handling": 0.839013849327178,
    "n_nitro": 0.8525292279198982
  },
  {
    "id": "pagani_huayra_bc",
    "name": "Pagani Huayra BC",
    "rank": 0,
    "car_class": "A",
    "top_speed": 350.0,
    "acceleration": 71.2,
    "handling": 46.1,
    "nitro": 73.11,
    "n_top_speed": 0.6289308176100629,
    "n_acceleration": 0.7865665046398587,
    "n_handling": 0.45280424319811413,
    "n_nitro": 0.8462785044565343
  },
  {
    "id": "mclaren_650s_gt3",
    "name": "Mclaren 650S GT3",
    "rank": 0,
    "car_class": "A",
    "top_speed": 357.0,
    "acceleration": 84.34,
    "handling": 85.82,
    "nitro": 78.22,
    "n_top_speed": 0.6415094339622641,
    "n_acceleration": 0.9317277949624393,
    "n_handling": 0.8429427364698948,
    "n_nitro": 0.9054288690820697
  },
  {
    "id": "lamborghini_sc18",
    "name": "Lamborghini SC18",
    "rank": 0,
    "car_class": "A",
    "top_speed": 350.0,
    "acceleration": 74.8,
    "handling": 45.33,
    "nitro": 64.96,
    "n_top_speed": 0.6289308176100629,
    "n_acceleration": 0.8263367211665931,
    "n_handling": 0.44524113544838423,
    "n_nitro": 0.7519388818150248
  },
  {
    "id": "ferrari_sf90_xx_stradale",
    "name": "Ferrari SF90 XX Stradale",
    "rank": 0,
    "car_class": "A",
    "top_speed": 361.2,
    "acceleration": 85.73,
    "handling": 79.17,
    "nitro": 62.85,
    "n_top_speed": 0.6490566037735849,
    "n_acceleration": 0.9470835174547062,
    "n_handling": 0.7776249877222277,
    "n_nitro": 0.7275147586526218
  },
  {
    "id": "ferrari_laferrari_aperta",
    "name": "Ferrari Laferrari Aperta",
    "rank": 0,
    "car_class": "A",
    "top_speed": 366.2,
    "acceleration": 81.03,
    "handling": 82.48,
    "nitro": 70.1,
    "n_top_speed": 0.658041329739443,
    "n_acceleration": 0.8951612903225807,
    "n_handling": 0.8101365288282094,
    "n_nitro": 0.8114365088551915
  },
  {
    "id": "lamborghini_sc20",
    "name": "Lamborghini SC20",
    "rank": 0,
    "car_class": "A",
    "top_speed": 353.4,
    "acceleration": 73.63,
    "handling": 51.04,
    "nitro": 40.77,
    "n_top_speed": 0.6350404312668463,
    "n_acceleration": 0.8134114007954043,
    "n_handling": 0.5013259994106669,
    "n_nitro": 0.4719296214839681
  },
  {
    "id": "pagani_utopia_coupe",
    "name": "Pagani Utopia Coupe",
    "rank": 0,
    "car_class": "A",
    "top_speed": 367.9,
    "acceleration": 81.03,
    "handling": 80.63,
    "nitro": 77.19,
    "n_top_speed": 0.6610961365678346,
    "n_acceleration": 0.8951612903225807,
    "n_handling": 0.791965425793144,
    "n_nitro": 0.8935061928463942
  },
  {
    "id": "genty_akylone",
    "name": "Genty Akylone",
    "rank": 0,
    "car_class": "A",
    "top_speed": 354.0,
    "acceleration": 75.7,
    "handling": 49.56,
    "nitro": 53.16,
    "n_top_speed": 0.6361185983827493,
    "n_acceleration": 0.8362792752982767,
    "n_handling": 0.4867891169826147,
    "n_nitro": 0.6153489987267045
  },
  {
    "id": "fv_frangivento_asfane",
    "name": "FV Frangivento Asfane",
    "rank": 0,
    "car_class": "A",
    "top_speed": 373.9,
    "acceleration": 82.03,
    "handling": 69.13,
    "nitro": 67.63,
    "n_top_speed": 0.6718778077268643,
    "n_acceleration": 0.906208572691118,
    "n_handling": 0.6790099204400353,
    "n_nitro": 0.7828452367172126
  },
  {
    "id": "techrules_at96_track_version",
    "name": "Techrules AT96 Track Version",
    "rank": 0,
    "car_class": "A",
    "top_speed": 364.6,
    "acceleration": 85.53,
    "handling": 75.74,
    "nitro": 69.65,
    "n_top_speed": 0.6551662174303684,
    "n_acceleration": 0.9448740609809987,
    "n_handling": 0.7439347804734309,
    "n_nitro": 0.8062275726357218
  },
  {
    "id": "noble_m600_speedster",
    "name": "Noble M600 Speedster",
    "rank": 0,
    "car_class": "A",
    "top_speed": 375.7,
    "acceleration": 81.03,
    "handling": 85.47,
    "nitro": 61.71,
    "n_top_speed": 0.6751123090745732,
    "n_acceleration": 0.8951612903225807,
    "n_handling": 0.8395049602200176,
    "n_nitro": 0.7143187868966315
  },
  {
    "id": "rimac_concept_one",
    "name": "Rimac Concept_One",
    "rank": 0,
    "car_class": "A",
    "top_speed": 368.5,
    "acceleration": 86.34,
    "handling": 84.08,
    "nitro": 54.53,
    "n_top_speed": 0.6621743036837376,
    "n_acceleration": 0.953822359699514,
    "n_handling": 0.8258520773990766,
    "n_nitro": 0.6312073156615349
  },
  {
    "id": "aston_valhalla_concept_car",
    "name": "Aston Valhalla Concept Car",
    "rank": 0,
    "car_class": "A",
    "top_speed": 377.4,
    "acceleration": 82.23,
    "handling": 81.76,
    "nitro": 59.55,
    "n_top_speed": 0.678167115902965,
    "n_acceleration": 0.9084180291648255,
    "n_handling": 0.8030645319713191,
    "n_nitro": 0.6893158930431763
  },
  {
    "id": "pagani_imola",
    "name": "Pagani Imola",
    "rank": 0,
    "car_class": "A",
    "top_speed": 378.9,
    "acceleration": 80.23,
    "handling": 72.17,
    "nitro": 71.14,
    "n_top_speed": 0.6808625336927223,
    "n_acceleration": 0.8863234644277509,
    "n_handling": 0.7088694627246832,
    "n_nitro": 0.8234749392290774
  },
  {
    "id": "ford_team_fordzilla_p1",
    "name": "Ford Team Fordzilla P1",
    "rank": 0,
    "car_class": "A",
    "top_speed": 382.0,
    "acceleration": 87.72,
    "handling": 53.75,
    "nitro": 60.72,
    "n_top_speed": 0.6864330637915543,
    "n_acceleration": 0.9690676093680954,
    "n_handling": 0.5279442098025734,
    "n_nitro": 0.7028591272137978
  },
  {
    "id": "jaguar_xjr_9",
    "name": "Jaguar XJR-9",
    "rank": 0,
    "car_class": "A",
    "top_speed": 412.3,
    "acceleration": 69.24,
    "handling": 59.33,
    "nitro": 84.95,
    "n_top_speed": 0.7408805031446541,
    "n_acceleration": 0.7649138311975254,
    "n_handling": 0.5827521854434731,
    "n_nitro": 0.9833314040976965
  },
  {
    "id": "lamborghini_countach_lpi_800_4",
    "name": "Lamborghini Countach LPI 800-4",
    "rank": 0,
    "car_class": "A",
    "top_speed": 373.4,
    "acceleration": 81.23,
    "handling": 85.96,
    "nitro": 72.4,
    "n_top_speed": 0.6709793351302785,
    "n_acceleration": 0.8973707467962881,
    "n_handling": 0.8443178469698457,
    "n_nitro": 0.8380599606435931
  },
  {
    "id": "de_tomaso_p72",
    "name": "DE Tomaso P72",
    "rank": 0,
    "car_class": "A",
    "top_speed": 375.6,
    "acceleration": 82.74,
    "handling": 75.24,
    "nitro": 71.18,
    "n_top_speed": 0.6749326145552561,
    "n_acceleration": 0.9140521431727795,
    "n_handling": 0.7390236715450348,
    "n_nitro": 0.8239379557819193
  },
  {
    "id": "mercedes_benz_vision_one_eleven",
    "name": "Mercedes-Benz Vision One-Eleven",
    "rank": 0,
    "car_class": "A",
    "top_speed": 384.3,
    "acceleration": 83.93,
    "handling": 81.26,
    "nitro": 81.68,
    "n_top_speed": 0.6905660377358491,
    "n_acceleration": 0.927198409191339,
    "n_handling": 0.7981534230429231,
    "n_nitro": 0.9454798009028823
  },
  {
    "id": "ferrari_fxx_k",
    "name": "Ferrari FXX K",
    "rank": 0,
    "car_class": "S",
    "top_speed": 350.0,
    "acceleration": 76.59,
    "handling": 38.45,
    "nitro": 64.95,
    "n_top_speed": 0.6289308176100629,
    "n_acceleration": 0.8461113566062749,
    "n_handling": 0.37766427659365487,
    "n_nitro": 0.7518231276768145
  },
  {
    "id": "lamborghini_autentica",
    "name": "Lamborghini Autentica",
    "rank": 0,
    "car_class": "S",
    "top_speed": 366.9,
    "acceleration": 78.86,
    "handling": 47.25,
    "nitro": 68.87,
    "n_top_speed": 0.6592991913746631,
    "n_acceleration": 0.8711886875828546,
    "n_handling": 0.46409979373342497,
    "n_nitro": 0.7971987498553074
  },
  {
    "id": "icona_vulcano_titanium",
    "name": "Icona Vulcano Titanium",
    "rank": 0,
    "car_class": "S",
    "top_speed": 370.0,
    "acceleration": 75.7,
    "handling": 35.26,
    "nitro": 53.84,
    "n_top_speed": 0.6648697214734951,
    "n_acceleration": 0.8362792752982767,
    "n_handling": 0.34633140163048814,
    "n_nitro": 0.6232202801250145
  },
  {
    "id": "w_motors_hypersport",
    "name": "W Motors Hypersport",
    "rank": 0,
    "car_class": "S",
    "top_speed": 395.0,
    "acceleration": 74.8,
    "handling": 37.0,
    "nitro": 39.79,
    "n_top_speed": 0.7097933513027853,
    "n_acceleration": 0.8263367211665931,
    "n_handling": 0.36342206070130634,
    "n_nitro": 0.46058571593934483
  },
  {
    "id": "raesr_tachyon_speed",
    "name": "Raesr Tachyon Speed",
    "rank": 0,
    "car_class": "S",
    "top_speed": 389.0,
    "acceleration": 73.45,
    "handling": 44.85,
    "nitro": 43.75,
    "n_top_speed": 0.6990116801437556,
    "n_acceleration": 0.8114228899690676,
    "n_handling": 0.44052647087712404,
    "n_nitro": 0.5064243546706795
  },
  {
    "id": "lamborghini_veneno",
    "name": "Lamborghini Veneno",
    "rank": 0,
    "car_class": "S",
    "top_speed": 355.0,
    "acceleration": 73.9,
    "handling": 53.52,
    "nitro": 61.51,
    "n_top_speed": 0.637915543575921,
    "n_acceleration": 0.8163941670349095,
    "n_handling": 0.5256850996955112,
    "n_nitro": 0.7120037041324228
  },
  {
    "id": "ats_automobili_gt",
    "name": "ATS Automobili GT",
    "rank": 0,
    "car_class": "S",
    "top_speed": 391.1,
    "acceleration": 81.47,
    "handling": 52.12,
    "nitro": 46.85,
    "n_top_speed": 0.7027852650494161,
    "n_acceleration": 0.9000220945647371,
    "n_handling": 0.5119339946960023,
    "n_nitro": 0.5423081375159162
  },
  {
    "id": "jaguar_xj220s_twr",
    "name": "Jaguar XJ220S TWR",
    "rank": 0,
    "car_class": "S",
    "top_speed": 383.2,
    "acceleration": 75.17,
    "handling": 60.57,
    "nitro": 82.21,
    "n_top_speed": 0.6885893980233603,
    "n_acceleration": 0.8304242156429519,
    "n_handling": 0.5949317355858953,
    "n_nitro": 0.9516147702280355
  },
  {
    "id": "lamborghini_egoista",
    "name": "Lamborghini Egoista",
    "rank": 0,
    "car_class": "S",
    "top_speed": 366.4,
    "acceleration": 84.48,
    "handling": 61.54,
    "nitro": 72.01,
    "n_top_speed": 0.6584007187780773,
    "n_acceleration": 0.9332744144940346,
    "n_handling": 0.6044592869069836,
    "n_nitro": 0.8335455492533859
  },
  {
    "id": "chrysler_me412",
    "name": "Chrysler ME412",
    "rank": 0,
    "car_class": "S",
    "top_speed": 399.1,
    "acceleration": 74.9,
    "handling": 66.52,
    "nitro": 63.39,
    "n_top_speed": 0.7171608265947889,
    "n_acceleration": 0.8274414494034469,
    "n_handling": 0.653373931833808,
    "n_nitro": 0.7337654821159857
  },
  {
    "id": "trion_nemesis",
    "name": "Trion Nemesis",
    "rank": 0,
    "car_class": "S",
    "top_speed": 434.0,
    "acceleration": 73.9,
    "handling": 39.45,
    "nitro": 35.92,
    "n_top_speed": 0.779874213836478,
    "n_acceleration": 0.8163941670349095,
    "n_handling": 0.3874864944504469,
    "n_nitro": 0.41578886445190416
  },
  {
    "id": "spania_gta_2015_gta_spano",
    "name": "Spania GTA 2015 GTA Spano",
    "rank": 0,
    "car_class": "S",
    "top_speed": 383.7,
    "acceleration": 81.2,
    "handling": 59.72,
    "nitro": 69.97,
    "n_top_speed": 0.6894878706199461,
    "n_acceleration": 0.897039328325232,
    "n_handling": 0.586582850407622,
    "n_nitro": 0.8099317050584558
  },
  {
    "id": "nissan_gt_r_neon_edition",
    "name": "Nissan GT-R Neon Edition",
    "rank": 0,
    "car_class": "S",
    "top_speed": 361.4,
    "acceleration": 87.55,
    "handling": 89.35,
    "nitro": 67.55,
    "n_top_speed": 0.6494159928122192,
    "n_acceleration": 0.9671895713654441,
    "n_handling": 0.8776151655043708,
    "n_nitro": 0.7819192036115291
  },
  {
    "id": "ferrari_sf90_stradale",
    "name": "Ferrari SF90 Stradale",
    "rank": 0,
    "car_class": "A",
    "top_speed": 361.2,
    "acceleration": 85.73,
    "handling": 79.17,
    "nitro": 62.85,
    "n_top_speed": 0.6490566037735849,
    "n_acceleration": 0.9470835174547062,
    "n_handling": 0.7776249877222277,
    "n_nitro": 0.7275147586526218
  },
  {
    "id": "fv_frangivento_sorpasso_gt3",
    "name": "FV Frangivento Sorpasso GT3",
    "rank": 0,
    "car_class": "S",
    "top_speed": 391.3,
    "acceleration": 85.7,
    "handling": 56.68,
    "nitro": 47.35,
    "n_top_speed": 0.7031446540880504,
    "n_acceleration": 0.9467520989836501,
    "n_handling": 0.5567233081229741,
    "n_nitro": 0.5480958444264382
  },
  {
    "id": "bugatti_veyron_16_4_ghrand_sport_vitesse",
    "name": "Bugatti Veyron 16.4 Ghrand Sport Vitesse",
    "rank": 0,
    "car_class": "S",
    "top_speed": 419.0,
    "acceleration": 81.06,
    "handling": 49.15,
    "nitro": 50.72,
    "n_top_speed": 0.7529200359389039,
    "n_acceleration": 0.8954927087936368,
    "n_handling": 0.48276200766132993,
    "n_nitro": 0.5871049890033568
  },
  {
    "id": "mclaren_senna",
    "name": "McLaren Senna",
    "rank": 0,
    "car_class": "S",
    "top_speed": 358.3,
    "acceleration": 82.91,
    "handling": 101.81,
    "nitro": 78.25,
    "n_top_speed": 0.6438454627133873,
    "n_acceleration": 0.9159301811754309,
    "n_handling": 1.0,
    "n_nitro": 0.905776131496701
  },
  {
    "id": "lamborghini_terzo_millennio",
    "name": "Lamborghini Terzo Millennio",
    "rank": 0,
    "car_class": "S",
    "top_speed": 394.3,
    "acceleration": 82.77,
    "handling": 52.84,
    "nitro": 69.29,
    "n_top_speed": 0.7085354896675652,
    "n_acceleration": 0.9143835616438356,
    "n_handling": 0.5190059915528926,
    "n_nitro": 0.802060423660146
  },
  {
    "id": "w_motors_fenyr_supersport",
    "name": "W Motors Fenyr SuperSport",
    "rank": 0,
    "car_class": "S",
    "top_speed": 405.0,
    "acceleration": 75.7,
    "handling": 37.7,
    "nitro": 60.97,
    "n_top_speed": 0.7277628032345014,
    "n_acceleration": 0.8362792752982767,
    "n_handling": 0.3702976132010608,
    "n_nitro": 0.7057529806690589
  },
  {
    "id": "aston_martin_valkyrie",
    "name": "Aston Martin Valkyrie",
    "rank": 0,
    "car_class": "S",
    "top_speed": 378.2,
    "acceleration": 80.03,
    "handling": 77.91,
    "nitro": 76.7,
    "n_top_speed": 0.6796046720575022,
    "n_acceleration": 0.8841140079540434,
    "n_handling": 0.7652489932226696,
    "n_nitro": 0.8878342400740826
  },
  {
    "id": "zenvo_ts1_gt_anniversary",
    "name": "Zenvo Ts1 GT Anniversary",
    "rank": 0,
    "car_class": "S",
    "top_speed": 418.2,
    "acceleration": 81.29,
    "handling": 46.66,
    "nitro": 63.43,
    "n_top_speed": 0.7514824797843666,
    "n_acceleration": 0.8980335837384005,
    "n_handling": 0.45830468519791767,
    "n_nitro": 0.7342284986688274
  },
  {
    "id": "rimac_concept_s",
    "name": "Rimac Concept S",
    "rank": 0,
    "car_class": "S",
    "top_speed": 376.3,
    "acceleration": 84.53,
    "handling": 79.9,
    "nitro": 69.86,
    "n_top_speed": 0.6761904761904762,
    "n_acceleration": 0.9338267786124614,
    "n_handling": 0.7847952067576859,
    "n_nitro": 0.8086584095381409
  },
  {
    "id": "automobili_pininfarina_battista",
    "name": "Automobili Pininfarina Battista",
    "rank": 0,
    "car_class": "S",
    "top_speed": 368.5,
    "acceleration": 88.49,
    "handling": 80.45,
    "nitro": 78.26,
    "n_top_speed": 0.6621743036837376,
    "n_acceleration": 0.9775740167918692,
    "n_handling": 0.7901974265789216,
    "n_nitro": 0.9058918856349115
  },
  {
    "id": "mclaren_speedtail",
    "name": "McLaren Speedtail",
    "rank": 0,
    "car_class": "S",
    "top_speed": 416.7,
    "acceleration": 81.11,
    "handling": 56.65,
    "nitro": 74.2,
    "n_top_speed": 0.7487870619946091,
    "n_acceleration": 0.8960450729120637,
    "n_handling": 0.5564286415872703,
    "n_nitro": 0.8588957055214724
  },
  {
    "id": "faraday_future_ffzero1",
    "name": "Faraday Future FFZERO1",
    "rank": 0,
    "car_class": "S",
    "top_speed": 423.0,
    "acceleration": 86.06,
    "handling": 42.83,
    "nitro": 51.7,
    "n_top_speed": 0.7601078167115903,
    "n_acceleration": 0.9507291206363235,
    "n_handling": 0.42068559080640405,
    "n_nitro": 0.5984488945479801
  },
  {
    "id": "koenigsegg_regera",
    "name": "Koenigsegg Regera",
    "rank": 0,
    "car_class": "S",
    "top_speed": 457.1,
    "acceleration": 80.88,
    "handling": 48.75,
    "nitro": 52.48,
    "n_top_speed": 0.8213836477987422,
    "n_acceleration": 0.8935041979673001,
    "n_handling": 0.4788331205186131,
    "n_nitro": 0.6074777173283944
  },
  {
    "id": "lamborghini_sian_fkp_37",
    "name": "Lamborghini Sian FKP 37",
    "rank": 0,
    "car_class": "S",
    "top_speed": 350.0,
    "acceleration": 74.8,
    "handling": 68.27,
    "nitro": 69.04,
    "n_top_speed": 0.6289308176100629,
    "n_acceleration": 0.8263367211665931,
    "n_handling": 0.6705628130831941,
    "n_nitro": 0.7991665702048849
  },
  {
    "id": "ford_mustang_rtr_spec_5_fd",
    "name": "Ford Mustang RTR Spec 5-FD",
    "rank": 0,
    "car_class": "B",
    "top_speed": 335.2,
    "acceleration": 75.65,
    "handling": 46.89,
    "nitro": 73.82,
    "n_top_speed": 0.602336028751123,
    "n_acceleration": 0.8357269111798499,
    "n_handling": 0.4605637953049799,
    "n_nitro": 0.8544970482694756
  },
  {
    "id": "ajlani_drakuma",
    "name": "Ajlani Drakuma",
    "rank": 0,
    "car_class": "S",
    "top_speed": 441.0,
    "acceleration": 81.56,
    "handling": 47.91,
    "nitro": 60.58,
    "n_top_speed": 0.7924528301886793,
    "n_acceleration": 0.9010163499779055,
    "n_handling": 0.4705824575189077,
    "n_nitro": 0.7012385692788516
  },
  {
    "id": "porsche_918_spyder_asphalt_edition",
    "name": "Porsche 918 Spyder Asphalt Edition",
    "rank": 0,
    "car_class": "A",
    "top_speed": 345.0,
    "acceleration": 76.59,
    "handling": 41.83,
    "nitro": 66.3,
    "n_top_speed": 0.6199460916442049,
    "n_acceleration": 0.8461113566062749,
    "n_handling": 0.410863372949612,
    "n_nitro": 0.767449936335224
  },
  {
    "id": "torino_design_super_sport",
    "name": "Torino Design Super Sport",
    "rank": 0,
    "car_class": "S",
    "top_speed": 405.3,
    "acceleration": 82.28,
    "handling": 62.3,
    "nitro": 75.81,
    "n_top_speed": 0.7283018867924529,
    "n_acceleration": 0.9089703932832524,
    "n_handling": 0.6119241724781456,
    "n_nitro": 0.8775321217733534
  },
  {
    "id": "bugatti_chiron",
    "name": "Bugatti Chiron",
    "rank": 0,
    "car_class": "S",
    "top_speed": 443.4,
    "acceleration": 84.4,
    "handling": 45.62,
    "nitro": 63.63,
    "n_top_speed": 0.7967654986522911,
    "n_acceleration": 0.9323906319045516,
    "n_handling": 0.4480895786268539,
    "n_nitro": 0.7365435814330362
  },
  {
    "id": "bxr_bailey_blade_gt1",
    "name": "BXR Bailey Blade GT1",
    "rank": 0,
    "car_class": "S",
    "top_speed": 449.5,
    "acceleration": 80.48,
    "handling": 46.87,
    "nitro": 70.66,
    "n_top_speed": 0.8077268643306379,
    "n_acceleration": 0.8890852850198852,
    "n_handling": 0.460367350947844,
    "n_nitro": 0.8179187405949763
  },
  {
    "id": "bugatti_divo",
    "name": "Bugatti Divo",
    "rank": 0,
    "car_class": "S",
    "top_speed": 396.0,
    "acceleration": 85.7,
    "handling": 61.48,
    "nitro": 73.99,
    "n_top_speed": 0.7115902964959568,
    "n_acceleration": 0.9467520989836501,
    "n_handling": 0.6038699538355761,
    "n_nitro": 0.856464868619053
  },
  {
    "id": "toroidion_1mw",
    "name": "Toroidion 1MW",
    "rank": 0,
    "car_class": "S",
    "top_speed": 460.6,
    "acceleration": 81.29,
    "handling": 60.32,
    "nitro": 54.19,
    "n_top_speed": 0.8276729559748428,
    "n_acceleration": 0.8980335837384005,
    "n_handling": 0.5924761811216973,
    "n_nitro": 0.6272716749623799
  },
  {
    "id": "bugatti_chiron_pur_sport",
    "name": "Bugatti Chiron Pur Sport",
    "rank": 0,
    "car_class": "S",
    "top_speed": 397.8,
    "acceleration": 87.01,
    "handling": 73.62,
    "nitro": 65.32,
    "n_top_speed": 0.7148247978436658,
    "n_acceleration": 0.961224038886434,
    "n_handling": 0.7231116786170317,
    "n_nitro": 0.7561060307906007
  },
  {
    "id": "koenigsegg_jesko",
    "name": "Koenigsegg Jesko",
    "rank": 0,
    "car_class": "S",
    "top_speed": 496.6,
    "acceleration": 80.07,
    "handling": 48.19,
    "nitro": 58.23,
    "n_top_speed": 0.8923629829290207,
    "n_acceleration": 0.8845558992487847,
    "n_handling": 0.4733326785188095,
    "n_nitro": 0.6740363467993981
  },
  {
    "id": "bugatti_centodieci",
    "name": "Bugatti Centodieci",
    "rank": 0,
    "car_class": "S",
    "top_speed": 402.7,
    "acceleration": 86.51,
    "handling": 62.58,
    "nitro": 77.09,
    "n_top_speed": 0.7236298292902066,
    "n_acceleration": 0.9557003977021654,
    "n_handling": 0.6146743934780473,
    "n_nitro": 0.8923486514642899
  },
  {
    "id": "w_motors_lykan_neon_edition",
    "name": "W Motors Lykan Neon Edition",
    "rank": 0,
    "car_class": "S",
    "top_speed": 429.3,
    "acceleration": 82.91,
    "handling": 52.87,
    "nitro": 65.41,
    "n_top_speed": 0.7714285714285715,
    "n_acceleration": 0.9159301811754309,
    "n_handling": 0.5193006580885964,
    "n_nitro": 0.7571478180344947
  },
  {
    "id": "bugatti_mistral",
    "name": "Bugatti Mistral",
    "rank": 0,
    "car_class": "S",
    "top_speed": 459.8,
    "acceleration": 81.56,
    "handling": 57.68,
    "nitro": 50.42,
    "n_top_speed": 0.8262353998203055,
    "n_acceleration": 0.9010163499779055,
    "n_handling": 0.5665455259797663,
    "n_nitro": 0.5836323648570436
  },
  {
    "id": "aspark_owl",
    "name": "Aspark Owl",
    "rank": 0,
    "car_class": "S",
    "top_speed": 414.7,
    "acceleration": 89.4,
    "handling": 51.75,
    "nitro": 51.27,
    "n_top_speed": 0.7451931716082659,
    "n_acceleration": 0.9876270437472383,
    "n_handling": 0.5082997740889893,
    "n_nitro": 0.5934714666049311
  },
  {
    "id": "rimac_nevera",
    "name": "Rimac Nevera",
    "rank": 0,
    "car_class": "S",
    "top_speed": 421.6,
    "acceleration": 87.71,
    "handling": 51.33,
    "nitro": 56.51,
    "n_top_speed": 0.7575920934411501,
    "n_acceleration": 0.9689571365444101,
    "n_handling": 0.5041744425891366,
    "n_nitro": 0.6541266350272021
  },
  {
    "id": "koenigsegg_agera_rs",
    "name": "Koenigsegg Agera RS",
    "rank": 0,
    "car_class": "S",
    "top_speed": 484.8,
    "acceleration": 79.67,
    "handling": 60.03,
    "nitro": 58.86,
    "n_top_speed": 0.8711590296495957,
    "n_acceleration": 0.8801369863013699,
    "n_handling": 0.5896277379432275,
    "n_nitro": 0.6813288575066558
  },
  {
    "id": "ssc_tuatara",
    "name": "SSC Tuatara",
    "rank": 0,
    "car_class": "S",
    "top_speed": 490.6,
    "acceleration": 82.51,
    "handling": 48.77,
    "nitro": 64.04,
    "n_top_speed": 0.8815813117699911,
    "n_acceleration": 0.911511268228016,
    "n_handling": 0.47902956487574894,
    "n_nitro": 0.7412895010996644
  },
  {
    "id": "bugatti_chiron_super_sport_300",
    "name": "Bugatti Chiron Super Sport 300+",
    "rank": 0,
    "car_class": "S",
    "top_speed": 453.6,
    "acceleration": 83.27,
    "handling": 60.63,
    "nitro": 41.7,
    "n_top_speed": 0.8150943396226416,
    "n_acceleration": 0.9199072028281042,
    "n_handling": 0.5955210686573028,
    "n_nitro": 0.4826947563375391
  },
  {
    "id": "koenigsegg_ccxr",
    "name": "Koenigsegg CCXR",
    "rank": 0,
    "car_class": "S",
    "top_speed": 412.2,
    "acceleration": 79.4,
    "handling": 79.09,
    "nitro": 71.51,
    "n_top_speed": 0.7407008086253369,
    "n_acceleration": 0.8771542200618648,
    "n_handling": 0.7768392102936843,
    "n_nitro": 0.8277578423428638
  },
  {
    "id": "bugatti_la_voiture_noire",
    "name": "Bugatti La Voiture Noire",
    "rank": 0,
    "car_class": "S",
    "top_speed": 443.4,
    "acceleration": 84.89,
    "handling": 54.63,
    "nitro": 63.79,
    "n_top_speed": 0.7967654986522911,
    "n_acceleration": 0.9378038002651349,
    "n_handling": 0.5365877615165504,
    "n_nitro": 0.7383956476444032
  },
  {
    "id": "czinger_21c",
    "name": "Czinger 21C",
    "rank": 0,
    "car_class": "S",
    "top_speed": 423.4,
    "acceleration": 89.07,
    "handling": 49.38,
    "nitro": 51.51,
    "n_top_speed": 0.760826594788859,
    "n_acceleration": 0.9839814405656209,
    "n_handling": 0.48502111776839213,
    "n_nitro": 0.5962495659219816
  },
  {
    "id": "deus_vayanne",
    "name": "Deus Vayanne",
    "rank": 0,
    "car_class": "S",
    "top_speed": 438.7,
    "acceleration": 86.55,
    "handling": 47.61,
    "nitro": 47.08,
    "n_top_speed": 0.7883198562443845,
    "n_acceleration": 0.9561422889969068,
    "n_handling": 0.4676357921618701,
    "n_nitro": 0.5449704826947563
  },
  {
    "id": "koenigsegg_gemera",
    "name": "Koenigsegg Gemera",
    "rank": 0,
    "car_class": "S",
    "top_speed": 413.1,
    "acceleration": 88.58,
    "handling": 66.06,
    "nitro": 48.36,
    "n_top_speed": 0.7423180592991914,
    "n_acceleration": 0.9785682722050376,
    "n_handling": 0.6488557116196837,
    "n_nitro": 0.5597870123856927
  },
  {
    "id": "zenvo_aurora_tur",
    "name": "Zenvo Aurora Tur",
    "rank": 0,
    "car_class": "S",
    "top_speed": 467.5,
    "acceleration": 81.73,
    "handling": 56.53,
    "nitro": 42.65,
    "n_top_speed": 0.8400718778077269,
    "n_acceleration": 0.9028943879805569,
    "n_handling": 0.5552499754444553,
    "n_nitro": 0.49369139946753093
  },
  {
    "id": "hennesey_venom_f5",
    "name": "Hennesey Venom F5",
    "rank": 0,
    "car_class": "S",
    "top_speed": 512.3,
    "acceleration": 80.66,
    "handling": 49.07,
    "nitro": 49.53,
    "n_top_speed": 0.9205750224618149,
    "n_acceleration": 0.8910737958462218,
    "n_handling": 0.4819762302327866,
    "n_nitro": 0.5733302465563144
  },
  {
    "id": "koenigsegg_cc850",
    "name": "Koenigsegg CC850",
    "rank": 0,
    "car_class": "S",
    "top_speed": 478.3,
    "acceleration": 82.37,
    "handling": 54.39,
    "nitro": 40.57,
    "n_top_speed": 0.8594788858939802,
    "n_acceleration": 0.9099646486964208,
    "n_handling": 0.5342304292309203,
    "n_nitro": 0.4696145387197592
  },
  {
    "id": "bugatti_bolide",
    "name": "Bugatti Bolide",
    "rank": 0,
    "car_class": "S",
    "top_speed": 497.1,
    "acceleration": 84.69,
    "handling": 51.07,
    "nitro": 21.71,
    "n_top_speed": 0.8932614555256065,
    "n_acceleration": 0.9355943437914274,
    "n_handling": 0.5016206659463707,
    "n_nitro": 0.25130223405486746
  },
  {
    "id": "koenigsegg_jesko_absolut",
    "name": "Koenigsegg Jesko Absolut",
    "rank": 0,
    "car_class": "S",
    "top_speed": 541.0,
    "acceleration": 83.36,
    "handling": 61.28,
    "nitro": 33.34,
    "n_top_speed": 0.97214734950584,
    "n_acceleration": 0.9209014582412727,
    "n_handling": 0.6019055102642177,
    "n_nitro": 0.3859242967936104
  },
  {
    "id": "devel_sixteen",
    "name": "Devel Sixteen",
    "rank": 0,
    "car_class": "S",
    "top_speed": 556.5,
    "acceleration": 81.38,
    "handling": 56.38,
    "nitro": 38.47,
    "n_top_speed": 1.0,
    "n_acceleration": 0.8990278391515687,
    "n_handling": 0.5537766427659365,
    "n_nitro": 0.4453061696955666
  }
]